[{"Title":"110 ਪਾਬੰਦੀਸ਼ੁਦਾ ਗੋਲੀਆਂ ਸਣੇ ਕਾਬੂ","Content":"ਸੁਭਾਨਪੁਰ ਪੁਲਿਸ ਨੇ ਪਾਬੰਦੀਸ਼ੁਦਾ ਗੋਲ਼ੀਆਂ ਸਣੇ ਇਕ ਵਿਅਕਤੀ ਨੂੰ ਕਾਬੂ ਕਰ ਕੇ ਉਸ ਨੰੂ ਜੇਲ੍ਹ ਭੇਜ ਦਿੱਤਾ ਹੈ। ਥਾਣਾ ਮੁਖੀ ਹਰਦੀਪ ਸਿੰਘ ਨੇ ਦੱਸਿਆ ਕਿ ਪੁਲਿਸ ਪਾਰਟੀ ਭੈੜੇ ਪੁਰਸ਼ਾਂ ਦੀ ਤਲਾਸ਼ ਦੇ ਸਬੰਧ ਵਿਚ ਥਾਣਾ ਸੁਭਾਨਪੁਰ ਤੋਂ ਪਿੰਡ ਡੋਗਰਾਂਵਾਲ, ਹਮੀਰਾ, ਲੱਖਣ ਖੋਲੇ ਆਦਿ ਨੂੰ ਜਾ ਰਹੇ ਸੀ ਕਿ ਖਾਸ ਮੁਖਬਰ  ਨੇ ਇਤਲਾਹ ਦਿੱਤੀ ਕਿ ਜਸਪ੍ਰਰੀਤ ਸਿੰਘ ਉਰਫ ਜੱਸ ਪਿੰਡ ਹਮੀਰਾ ਥਾਣਾ ਸੁਭਾਨਪੁਰ ਜੋ ਰੇਲਵੇ ਫਾਟਕ ਹਮੀਰਾ ਦੇ ਨੇੜੇ ਕਰਿਆਨੇ ਦੀ ਦੁਕਾਨ ਕਰਦਾ ਹੈ ਅਤੇ ਕਰਿਆਨੇ ਦੀ ਦੁਕਾਨ ਦੀ ਆੜ ਵਿਚ ਪਾਬੰਦੀਸ਼ੁਦਾ ਗੋਲੀਆਂ ਵੇਚਣ ਦਾ ਧੰਦਾ ਕਰਦਾ ਹੈ।","PublishDate":"Wed, 28 Jun 2023 14:11:45 +00:00","Link":"https://www.punjabijagran.com/punjab/kapurthala-1-arrested-with-110-banned-pills-9247344.html"},{"Title":"2.767 ਕਿਲੋ ਗਾਂਜੇ ਸਮੇਤ ਦੋ ਮੁਲਜ਼ਮ ਗਿ੍ਫ਼ਤਾਰ","Content":"ਸਟਾਫ਼ ਰਿਪੋਰਟਰ, ਚੰਡੀਗੜ੍ਹ : ਪੁਲਿਸ ਨੇ ਦੋ ਮੁਲਜ਼ਮਾਂ ਨੂੰ 2.767 ਕਿਲੋ ਗਾਂਜੇ ਸਮੇਤ ਕਾਬੂ ਕੀਤਾ ਹੈ। ਮੁਲਜ਼ਮਾਂ ਦੀ ਪਛਾਣ ਤਸਕਰ ਚਨੋ ਮੰਡਲ ਅਤੇ ਦਬੇਸ਼ਵਰੀ ਯਾਦਵ ਵਜੋਂ ਹੋਈ ਹੈ। ਪੁਲਿਸ ਨੇ ਮੁਲਜ਼ਮ ਮੰਡਲ","PublishDate":"Wed, 28 Jun 2023 14:08:02 +00:00","Link":"https://www.punjabijagran.com/punjab/chandigarh-two-accused-arrested-along-with-2767-kg-ganja-9247343.html"},{"Title":"ਕਿਸਾਨਾਂ ਦਾ ਧਰਨਾ 21ਵੇਂ ਦਿਨ ਵੀ ਜਾਰੀ","Content":"ਭਾਰਤੀ ਕਿਸਾਨ ਯੂਨੀਅਨ ਏਕਤਾ ਡਕੌਂਦਾ ਵੱਲੋਂ ਕਿਸਾਨਾਂ ਦੀ ਮੁਆਵਜ਼ਾ ਰਾਸ਼ੀ ਲਈ ਤਹਿਸੀਲ ਕੰਪਲੈਕਸ ਵਿਚ ਦਿੱਤਾ ਜਾ ਰਿਹਾ ਧਰਨਾ ਲਗਾਤਾਰ 21ਵੇਂ ਦਿਨ ਵੀ ਜਾਰੀ ਰਿਹਾ। ਅੱਜ ਧਰਨੇ ਨੂੰ ਭਾਰਤੀ ਕਿਸਾਨ ਯੂਨੀਅਨ ਏਕਤਾ ਡਕੌਂਦਾ ਦੇ ਜ਼ਿਲ੍ਹਾ ਪ੍ਰਧਾਨ ਕਰਮਜੀਤ ਸਿੰਘ ਚੈਨਾ, ਜ਼ਿਲ੍ਹਾ ਖਜ਼ਾਨਚੀ ਗੁਰਮੇਲ ਸਿੰਘ ਹੇਰ ਚੈਨਾ, ਜ਼ਲਿ੍ਹਾ ਮੀਤ ਪ੍ਰਧਾਨ ਗੁਰਜੀਤ ਸਿੰਘ ਨੰਬਰਦਾਰ ਦਬੜੀਖਾਨਾ, ਜ਼ਲਿ੍ਹਾ ਜਰਨਲ ਸਕੱਤਰ ਸੁਖਦੇਵ ਸਿੰਘ ਬਹਿਬਲ ਕਲਾਂ, ਜ਼ਿਲ੍ਹਾ ਪ੍ਰਰੈੱਸ ਸਕੱਤਰ ਜਗਜੀਤ ਸਿੰਘ ਡੋਡ, ਹਰਦੇਵ ਸਿੰਘ ਘਣੀਏ ਵਾਲਾ, ਜਸਵਿੰਦਰ ਸਿੰਘ ਡੋਡ ਤੇ ਨਾਇਬ ਸਿੰਘ ਢੈਪਈ ਨੇ ਕਿਹਾ ਕਿ ਦਬੜੀਖਾਨਾ ਪਿੰਡ ਦੇ ਕੁਝ ਕਿਸਾਨਾਂ ਦੇ ਖਾਤਿਆਂ ਵਿਚ ਮੁਆਵਜ਼ਾ ਰਾਸ਼ੀ ਪਾਈ","PublishDate":"Wed, 28 Jun 2023 14:08:02 +00:00","Link":"https://www.punjabijagran.com/punjab/faridkot-farmers-condemned-the-attitude-of-sdm-jaito-9247342.html"},{"Title":"Big Breaking : ਬਰਨਾਲਾ ਪੁਲਿਸ ਦੀ ਹਿਰਾਸਤ 'ਚੋ  ਤਿੰਨ ਅਪਰਾਧੀ ਹੋਏ ਫ਼ਰਾਰ, ਮੱਕੀ ਦੇ ਖੇਤ 'ਚ ਭਾਲ ਕਰ ਰਹੀ ਪੁਲਿਸ","Content":"ਬਰਨਾਲਾ ਪੁਲਿਸ ਦੀ ਹਿਰਾਸਤ 'ਚੋ  ਤਿੰਨ ਅਪਰਾਧੀ  ਫ਼ਰਾਰ ਹੋਣ ਦਾ ਸਮਾਚਾਰ ਹੈ। ਬੁੱਧਵਾਰ ਨੂੰ ਨਕੋਦਰ ਤੋਂ ਤਿੰਨ ਗੈਂਗਸਟਰਾਂ ਨੂੰ ਪੁਲਿਸ ਥਾਣਾ ਸਿਟੀ ਬਰਨਾਲਾ ਵੱਲੋਂ ਇੱਕ ਗੰਭੀਰ ਅਪਰਾਧ ਦੇ ਸਬੰਧ ਵਿੱਚ ਪੁੱਛਗਿੱਛ ਲਈ ਬਰਨਾਲਾ ਲਿਆਂਦਾ ਗਿਆ ਸੀ, ਜਿਨ੍ਹਾਂ ਨੂੰ ਪੁਲਿਸ ਵੱਲੋਂ ਇੱਕ ਨਿੱਜੀ ਥਾਂ 'ਤੇ ਰੱਖਿਆ ਗਿਆ ਸੀ। ਫ਼ਰਾਰ ਹੋਏ ਗੈਂਗਸਟਰਾਂ ਨੂੰ ਕਾਬੂ ਕਰਨ ਲਈ ਬਰਨਾਲਾ ਜ਼ਿਲ੍ਹੇ ਦੀ ਪੁਲਿਸ, ਐੱਸਟੀਐੱਫ ਦੀ ਟੀਮ, ਕਮਾਂਡੋ ਅਤੇ ਹੋਰ ਪੁਲਿਸ ਅਧਿਕਾਰੀ ਤੇ ਕਰਮਚਾਰੀ ਡ੍ਰੋਨ ਦੀ ਮਦਦ ਨਾਲ ਉਨ੍ਹਾਂ ਨੂੰ ਲੱਭਣ ਲਈ ਪਸੀਨਾ ਵਹਾਉਂਦੇ ਰਹੇ।","PublishDate":"Wed, 28 Jun 2023 14:07:35 +00:00","Link":"https://www.punjabijagran.com/punjab/barnala-big-breaking-three-criminals-escaped-from-the-custody-of-barnala-police-9247329.html"},{"Title":"ਨਵੀਂ ਅਨਾਜ ਮੰਡੀ ਬਣਨ ਨਾਲ ਕਿਸਾਨਾਂ ਤੇ ਆੜ੍ਹਤੀਆਂ ਨੂੰ ਮੁਸ਼ਕਲਾਂ ਤੋਂ ਮਿਲੇਗਾ ਛੁਟਕਾਰਾ : ਪਿੰ੍. ਬੁੱਧ ਰਾਮ","Content":"ਪਿਛਲੇ ਦਿਨ੍ਹੀਂ ਮੁੱਖ ਮੰਤਰੀ ਭਗਵੰਤ ਮਾਨ ਵੱਲੋਂ ਬੁਢਲਾਡਾ ਦੌਰੇ ਦੌਰਾਨ ਆੜ੍ਹਤੀਆ ਵਰਗ ਦੀ ਮੁੱਖ ਮੰਗ ਨੂੰ ਧਿਆਨ ਵਿੱਚ ਰੱਖਦਿਆਂ ਨਵੀਂ ਅਨਾਜ ਮੰਡੀ ਦੇ ਕੀਤੇ ਐਲਾਨ ਤੋਂ ਬਾਅਦ ਅੱਜ ਹਲਕਾ ਵਿਧਾਇਕ ਪਿੰ੍ਸੀਪਲ ਬੁੱਧ ਰਾਮ ਦਾ ਸਨਮਾਨ ਸਮਾਰੋਹ ਕੀਤਾ ਗਿਆ।","PublishDate":"Wed, 28 Jun 2023 14:07:06 +00:00","Link":"https://www.punjabijagran.com/punjab/mansa-anaz-mandi-9247341.html"},{"Title":"ਲੋੜਵੰਦ ਪਰਿਵਾਰਾਂ ਦੀ ਮਦਦ ਕਰ ਕੇ ਮਿਲਦੈ ਸਕੂਨ : ਪੱਡਾ","Content":"ਜੋ ਮਨ ਨੂੰ ਸਕੂਨ ਲੋੜਵੰਦਾਂ ਦੀ ਸਹਾਇਤਾ ਕਰ ਕੇ ਮਿਲਦਾ ਹੈ, ਉਸ ਨਾਲ ਦੀ ਕੋਈ ਚੀਜ਼ ਨਹੀਂ ਹੈ। ਇਨ੍ਹਾਂ ਸ਼ਬਦਾਂ ਦਾ ਪ੍ਰਗਟਾਵਾ ਆਮ ਆਦਮੀ ਪਾਰਟੀ ਦੇ ਸੀਨੀਅਰ ਆਗੂ ਅਤੇ ਐੱਨਆਰਆਈ ਸਭਾ ਜਰਮਨੀ ਦੇ ਪ੍ਰਧਾਨ ਸੁਖਵੰਤ ਸਿੰਘ ਪੱਡਾ ਨੇ ਪਿੰਡ ਵਰਿਆਂਹ ਦੋਨਾਂ ਵਿਖੇ ਪਰਮਜੀਤ ਦੀ ਲੜਕੀ ਜਸਵਿੰਦਰ ਕੌਰ ਦੇ ਵਿਆਹ ਸਮਾਗਮ 'ਚ ਸ਼ਿਰਕਤ ਕਰਦੇ ਹੋਏ ਮਾਲੀ ਸਹਾਇਤਾ ਦੇ ਨਾਲ-ਨਾਲ ਲੜਕੀ ਨੂੰ ਆਸ਼ੀਰਵਾਦ ਦੇਣ ਮੌਕੇ ਕੀਤਾ।","PublishDate":"Wed, 28 Jun 2023 14:07:05 +00:00","Link":"https://www.punjabijagran.com/punjab/kapurthala-helping-needy-families-brings-peace-of-mind-padda-9247340.html"},{"Title":"ਵਿੰਬਲਡਨ 'ਚ ਸਿਖ਼ਰਲੇ ਦਰਜੇ ਨਾਲ ਸ਼ਾਮਲ ਹੋਣਗੇ ਅਲਕਰਾਜ਼ ਤੇ ਸਵੀਆਤੇਕ","Content":"ਵਿੰਬਲਡਨ (ਏਪੀ) : ਚਾਰ ਵਾਰ ਦੇ ਸਾਬਕਾ ਜੇਤੂ ਨੋਵਾਕ ਜੋਕੋਵਿਕ ਨੂੰ ਪਛਾੜਦੇ ਹੋਏ ਕਾਰਲੋਸ ਅਲਕਰਾਜ਼ ਤੇ ਇਗਾ ਸਵੀਆਤੇਕ ਵਿੰਬਲਡਨ 'ਚ ਸਿਖਰਲੇ ਦਰਜੇ ਨਾਲ ਸ਼ਾਮਲ ਹੋਣਗੇ ਕਿਉਂਕਿ ਇਸ ਵਾਰ ਆਲ ਇੰਗਲੈਂਡ ਕਲੱਬ ਨੇ ਵੀ ਏਟੀਪੀ ਤੇ ਡਬਲਿਊਟੀਏ ਰੈਂਕਿੰਗ ਨੂੰ ਹੀ ਮਾਨਤਾ ਦਿੱਤੀ ਹੈ। ਸੋਮਵਾਰ ਨੂੰ ਸਪੈਨਿਸ਼ ਖਿਡਾਰੀ ਕਾਰਲੋਸ ਅਲਕਰਾਜ਼ ਨੇ ਏਟੀਪ","PublishDate":"Wed, 28 Jun 2023 14:04:19 +00:00","Link":"https://www.punjabijagran.com/sports/general-tennis-diary-9247339.html"},{"Title":"ਵਿਕਾਸ ਫੰਡ ਦੀ ਕਟੌਤੀ ਵਿਰੁੱਧ ਮੁੱਖ ਮੰਤਰੀ ਨੂੰ ਭੇਜਿਆ ਮੰਗ-ਪੱਤਰ","Content":"ਐੱਸਸੀਬੀਸੀ ਸਮਾਜ ਅਤੇ ਮੁਲਾਜ਼ਮ ਵਰਗ ਦੇ ਹੱਕਾਂ ਦੀ ਆਵਾਜ਼ ਬੁਲੰਦ ਕਰਨ ਵਾਲੀ ਗਜਟਿਡ ਨਾਨ-ਗਜਟਿਡ ਐੱਸਸੀਬੀਸੀ ਇੰਪਲਾਈਜ਼ ਫੈੱਡਰੇਸ਼ਨ ਇਕਾਈ ਕਪੂਰਥਲਾ ਦੇ ਪ੍ਰਧਾਨ ਅਤੇ ਐਡੀਸ਼ਨਲ ਸਟੇਟ ਪ੍ਰਧਾਨ ਸਤਵੰਤ ਟੂਰਾ, ਮਨਜੀਤ ਗਾਟ, ਗਿਆਨ ਚੰਦ ਵਾਹਦ, ਲਖਵੀਰ ਚੰਦ, ਬਲਵਿੰਦਰ ਨਿਧੜਕ ਦੀ ਅਗਵਾਈ ਅਧੀਨ ਇਕ ਵਫ਼ਦ ਨੇ ਸਟੇਟ ਕਮੇਟੀ ਵੱਲੋਂ ਲਏ ਫ਼ੈਸਲੇ ਅਨੁਸਾਰ ਇਕ ਮੰਗ-ਪੱਤਰ, ਮੁੱਖ ਮੰਗਾਂ ਨੂੰ ਲੈ ਕੇ, ਜਿਸ ਵਿਚ ਹਾਲ ਹੀ ਵਿਚ ਪੰਜਾਬ ਸਰਕਾਰ ਵੱਲੋਂ ਜਿੱਥੇ ਮੁਲਾਜ਼ਮ ਵਰਗ 'ਤੇ ਪਹਿਲਾਂ ਹੀ ਵਿਕਾਸ ਫੰਡ ਜਬਰੀ 200 ਰੁਪਏ ਲਾਇਆ ਹੋਇਆ ਹੈ","PublishDate":"Wed, 28 Jun 2023 14:02:29 +00:00","Link":"https://www.punjabijagran.com/punjab/kapurthala-demand-letter-sent-to-chief-minister-punjab-against-reduction-of-forced-development-fund-of-pensioners-9247337.html"},{"Title":"ਹੈਵੀ ਲਾਇਸੰਸ ਬਣਾਉਣ ਬਦਲੇ ਰਿਸ਼ਵਤ ਲੈਣ ਦੇ ਦੋਸ਼ ਹੇਠ ਪ੍ਰਰਾਈਵੇਟ ਏਜੰਟ ਗਿ੍ਫ਼ਤਾਰ","Content":"ਸਟਾਫ਼ ਰਿਪੋਰਟਰ, ਚੰਡੀਗੜ੍ਹ : ਪੰਜਾਬ ਵਿਜੀਲੈਂਸ ਬਿਊਰੋ ਨੇ ਲਾਜ਼ਮੀ ਡਰਾਈਵਿੰਗ ਟੈਸਟ ਦਿੱਤੇ ਬਿਨਾਂ ਹੈਵੀ ਡਰਾਈਵਿੰਗ ਲਾਇਸੰਸ ਬਣਾਉਣ ਬਦਲੇ 500 ਰੁਪਏ ਰਿਸ਼ਵਤ ਲੈਣ ਦੇ ਦੋਸ਼ ਹੇਠ ਇੱਕ ਪ੍ਰਰਾਈਵੇਟ ਏਜੰਟ ਨੂੰ ਗਿ੍ਫ਼ਤਾਰ ਕੀਤਾ ਹੈ।","PublishDate":"Wed, 28 Jun 2023 14:02:29 +00:00","Link":"https://www.punjabijagran.com/punjab/chandigarh-private-agent-arrested-on-the-charge-of-taking-bribe-in-exchange-for-making-heavy-license-without-driving-test-9247338.html"},{"Title":"ਸ਼ਰਧਾ ਤੇ ਸਤਿਕਾਰ ਸਹਿਤ ਮਨਾਇਆ ਮੀਰੀ ਪੀਰੀ ਦਿਵਸ","Content":"ਗੁਰਦੁਆਰਾ ਸ਼੍ਰੋਮਣੀ ਭਗਤ ਬਾਬਾ ਨਾਮਦੇਵ ਜੀ ਲਲਹੇੜੀ ਰੋਡ ਖੰਨਾ ਵਿਖੇ ਮੀਰੀ ਪੀਰੀ ਦਿਵਸ ਬਹੁਤ ਹੀ ਸ਼ਰਧਾ ਤੇ ਸਤਿਕਾਰ ਸਹਿਤ ਮਨਾਇਆ ਗਿਆ। ਵੱਡੀ ਗਿਣਤੀ 'ਚ ਇਲਾਕੇ ਦੀ ਸੰਗਤ ਨੇ ਸ਼ਮੂਲੀਅਤ ਕੀਤੀ, ਜਿਸ 'ਚ ਸਵੇਰੇ ਨਿਤਨੇਮ ਦੀਆਂ ਬਾਣੀਆਂ ਤੇ ਸ੍ਰੀ ਸੁਖਮਨੀ ਸਾਹਿਬ ਦੇ ਪਾਠ ਦੇ ਭੋਗ ਉਪਰੰਤ ਹਜ਼ੂਰੀ ਰਾਗੀ ਭਾਈ ਪਰਮਜੀਤ ਸਿੰਘ ਰਹਿਮਤ ਦੇ ਜਥੇ ਵੱਲੋਂ ਮੀਰੀ ਪੀਰੀ ਦੇ ਇਤਹਾਸ ਤੇ ਗੁਰਬਾਣੀ ਦੇ ਮਨੋਹਰ ਕੀਰਤਨ ਤੇ ਕਥਾ ਨਾਲ ਸੰਗਤ ਨੂੰ ਨਿਹਾਲ ਕੀਤਾ। \nਭਾਈ ਗੁਰਸ਼ਰਨ ਸਿੰਘ ਵੱਲੋਂ ਸਰਬੱਤ ਦੇ ਭਲੇ ਦੀ ਅਰਦਾਸ ਉਪਰੰਤ ਚਾਹ ਦੇ ਲੰਗਰ ਅਤੁੱਟ ਵਰਤਾਏ ਗਏ। ਅੱਜ ਦੇ ਦਿਨ ਛੇਵੇਂ ਗੁਰੂ ਸ੍ਰੀ ਗੁਰੂ ਹਰਗੋਬਿੰਦ ਸਾਹਿਬ ਜੀ ਨੇ ਅਕਾਲ ਤਖ਼ਤ ਦੇ ਸਨਮੁ","PublishDate":"Wed, 28 Jun 2023 14:01:33 +00:00","Link":"https://www.punjabijagran.com/punjab/ludhiana-miri-piri-day-was-celebrated-with-reverence-and-respect-9247336.html"},{"Title":"UP ‘ਚ ਭੀਮ ਆਰਮੀ ਚੀਫ ਚੰਦਰਸ਼ੇਖਰ ‘ਤੇ ਜਾਨਲੇਵਾ ਹਮਲਾ, ਕਾਰ ਤੋਂ ਆਏ ਹਮਲਾਵਰਾਂ ਨੇ ਚਲਾਈਆਂ ਗੋਲੀਆਂ","Content":"<p>ਸਹਾਰਨਪੁਰ: ਉੱਤਰ ਪ੍ਰਦੇਸ਼ &#8216;ਚ ਸਹਾਰਨਪੁਰ ਦੇ ਦੇਵਬੰਦ ਇਲਾਕੇ &#8216;ਚ ਭੀਮ ਆਰਮੀ ਚੀਫ ਚੰਦਰਸ਼ੇਖਰ &#8216;ਤੇ ਜਾਨਲੇਵਾ ਹਮਲਾ ਹੋਇਆ ਹੈ। ਉਹ ਦਿੱਲੀ</p>\n<p>The post <a rel=\"nofollow\" href=\"https://punjabnewsusa.com/8249/india-news/up-%e0%a8%9a-%e0%a8%ad%e0%a9%80%e0%a8%ae-%e0%a8%86%e0%a8%b0%e0%a8%ae%e0%a9%80-%e0%a8%9a%e0%a9%80%e0%a8%ab-%e0%a8%9a%e0%a9%b0%e0%a8%a6%e0%a8%b0%e0%a8%b8%e0%a8%bc%e0%a9%87%e0%a8%96%e0%a8%b0/\">UP &#8216;ਚ ਭੀਮ ਆਰਮੀ ਚੀਫ ਚੰਦਰਸ਼ੇਖਰ &#8216;ਤੇ ਜਾਨਲੇਵਾ ਹਮਲਾ, ਕਾਰ ਤੋਂ ਆਏ ਹਮਲਾਵਰਾਂ ਨੇ ਚਲਾਈਆਂ ਗੋਲੀਆਂ</a> appeared first on <a rel=\"nofollow\" href=\"https://punjabnewsusa.com\">Punjab News USA</a>.</p>\n","PublishDate":"Wed, 28 Jun 2023 14:04:17 +00:00","Link":"https://punjabnewsusa.com/8249/india-news/up-%e0%a8%9a-%e0%a8%ad%e0%a9%80%e0%a8%ae-%e0%a8%86%e0%a8%b0%e0%a8%ae%e0%a9%80-%e0%a8%9a%e0%a9%80%e0%a8%ab-%e0%a8%9a%e0%a9%b0%e0%a8%a6%e0%a8%b0%e0%a8%b8%e0%a8%bc%e0%a9%87%e0%a8%96%e0%a8%b0/"},{"Title":"ਬਰੇਲੀ ਤੋਂ ਪਰਤ ਰਹੇ ਪਿਓ ਤੇ ਦੋ ਪੁੱਤਰਾਂ ਦੀ ਮੌਤ","Content":"<p>ਬਰੇਲੀ (ਯੂਪੀ): ਇਸ ਜ਼ਿਲ੍ਹੇ ਫਤਹਿਗੰਜ ਟੌਲ ਪਲਾਜ਼ਾ ਨੇੜੇ ਟਰੱਕ ਵੱਲੋਂ ਕਾਰ ਨੂੰ ਟੱਕਰ ਮਾਰਨ ਕਾਰਨ ਪੰਜਾਬ ਦੇ 45 ਸਾਲਾ ਵਿਅਕਤੀ</p>\n<p>The post <a rel=\"nofollow\" href=\"https://punjabnewsusa.com/8241/punjab-news/%e0%a8%ac%e0%a8%b0%e0%a9%87%e0%a8%b2%e0%a9%80-%e0%a8%a4%e0%a9%8b%e0%a8%82-%e0%a8%aa%e0%a8%b0%e0%a8%a4-%e0%a8%b0%e0%a8%b9%e0%a9%87-%e0%a8%aa%e0%a8%bf%e0%a8%93-%e0%a8%a4%e0%a9%87-%e0%a8%a6%e0%a9%8b/\">ਬਰੇਲੀ ਤੋਂ ਪਰਤ ਰਹੇ ਪਿਓ ਤੇ ਦੋ ਪੁੱਤਰਾਂ ਦੀ ਮੌਤ</a> appeared first on <a rel=\"nofollow\" href=\"https://punjabnewsusa.com\">Punjab News USA</a>.</p>\n","PublishDate":"Tue, 27 Jun 2023 13:32:31 +00:00","Link":"https://punjabnewsusa.com/8241/punjab-news/%e0%a8%ac%e0%a8%b0%e0%a9%87%e0%a8%b2%e0%a9%80-%e0%a8%a4%e0%a9%8b%e0%a8%82-%e0%a8%aa%e0%a8%b0%e0%a8%a4-%e0%a8%b0%e0%a8%b9%e0%a9%87-%e0%a8%aa%e0%a8%bf%e0%a8%93-%e0%a8%a4%e0%a9%87-%e0%a8%a6%e0%a9%8b/"},{"Title":"ਪੱਤਰਕਾਰ ਸਬਰੀਨਾ ਸਦੀਕੀ ਨੂੰ ਨਿਸ਼ਾਨਾ ਬਣਾਏ ਜਾਣ ਦੀ ਵਾਈਟ ਹਾਊਸ ਵੱਲੋਂ ਨਿੰਦਾ","Content":"<p>ਵਾਸ਼ਿੰਗਟਨ: ਵਾਇਟ ਹਾਊਸ ਨੇ ਰਾਸ਼ਟਰਪਤੀ ਜੋਅ ਬਾਈਡਨ ਦੇ ਨਾਲ ਸਾਂਝੀ ਪ੍ਰੈੱਸ ਕਾਨਫ਼ਰੰਸ ’ਚ ਪ੍ਰਧਾਨ ਮੰਤਰੀ ਨਰਿੰਦਰ ਮੋਦੀ ਤੋਂ ਸਵਾਲ ਪੁੱਛਣ</p>\n<p>The post <a rel=\"nofollow\" href=\"https://punjabnewsusa.com/8229/world-news/%e0%a8%aa%e0%a9%b1%e0%a8%a4%e0%a8%b0%e0%a8%95%e0%a8%be%e0%a8%b0-%e0%a8%b8%e0%a8%ac%e0%a8%b0%e0%a9%80%e0%a8%a8%e0%a8%be-%e0%a8%b8%e0%a8%a6%e0%a9%80%e0%a8%95%e0%a9%80-%e0%a8%a8%e0%a9%82%e0%a9%b0/\">ਪੱਤਰਕਾਰ ਸਬਰੀਨਾ ਸਦੀਕੀ ਨੂੰ ਨਿਸ਼ਾਨਾ ਬਣਾਏ ਜਾਣ ਦੀ ਵਾਈਟ ਹਾਊਸ ਵੱਲੋਂ ਨਿੰਦਾ</a> appeared first on <a rel=\"nofollow\" href=\"https://punjabnewsusa.com\">Punjab News USA</a>.</p>\n","PublishDate":"Tue, 27 Jun 2023 13:29:08 +00:00","Link":"https://punjabnewsusa.com/8229/world-news/%e0%a8%aa%e0%a9%b1%e0%a8%a4%e0%a8%b0%e0%a8%95%e0%a8%be%e0%a8%b0-%e0%a8%b8%e0%a8%ac%e0%a8%b0%e0%a9%80%e0%a8%a8%e0%a8%be-%e0%a8%b8%e0%a8%a6%e0%a9%80%e0%a8%95%e0%a9%80-%e0%a8%a8%e0%a9%82%e0%a9%b0/"},{"Title":"ਕੇਜਰੀ ਦੀ ਰਿਹਾਇਸ਼ ਦੀ ‘ਮੁੜਉਸਾਰੀ’ ’ਚ ‘ਬੇਨਿਯਮੀਆਂ’ ਦਾ ਆਡਿਟ ਕਰੇਗਾ ਕੈਗ","Content":"<p>ਨਵੀਂ ਦਿੱਲੀ: ਭਾਰਤ ਦੇ ਕੰਪਟਰੋਲਰ ਅਤੇ ਆਡੀਟਰ ਜਨਰਲ (ਕੈਗ) ਦਿੱਲੀ ਦੇ ਮੁੱਖ ਮੰਤਰੀ ਅਰਵਿੰਦ ਕੇਜਰੀਵਾਲ ਦੀ ਰਿਹਾਇਸ਼ ਦੀ ‘ਮੁੜਉਸਾਰੀ’ ’ਚ</p>\n<p>The post <a rel=\"nofollow\" href=\"https://punjabnewsusa.com/8228/india-news/%e0%a8%95%e0%a9%87%e0%a8%9c%e0%a8%b0%e0%a9%80-%e0%a8%a6%e0%a9%80-%e0%a8%b0%e0%a8%bf%e0%a8%b9%e0%a8%be%e0%a8%87%e0%a8%b8%e0%a8%bc-%e0%a8%a6%e0%a9%80-%e0%a8%ae%e0%a9%81%e0%a9%9c%e0%a8%89/\">ਕੇਜਰੀ ਦੀ ਰਿਹਾਇਸ਼ ਦੀ ‘ਮੁੜਉਸਾਰੀ’ ’ਚ ‘ਬੇਨਿਯਮੀਆਂ’ ਦਾ ਆਡਿਟ ਕਰੇਗਾ ਕੈਗ</a> appeared first on <a rel=\"nofollow\" href=\"https://punjabnewsusa.com\">Punjab News USA</a>.</p>\n","PublishDate":"Tue, 27 Jun 2023 13:23:08 +00:00","Link":"https://punjabnewsusa.com/8228/india-news/%e0%a8%95%e0%a9%87%e0%a8%9c%e0%a8%b0%e0%a9%80-%e0%a8%a6%e0%a9%80-%e0%a8%b0%e0%a8%bf%e0%a8%b9%e0%a8%be%e0%a8%87%e0%a8%b8%e0%a8%bc-%e0%a8%a6%e0%a9%80-%e0%a8%ae%e0%a9%81%e0%a9%9c%e0%a8%89/"},{"Title":"ਇਕ ਦਹਾਕੇ ’ਚ ਕਰੀਬ 70,000 ਭਾਰਤੀਆਂ ਨੇ ਸਰੰਡਰ ਕੀਤੇ ਅਪਣੇ ਪਾਸਪੋਰਟ","Content":"<p>ਨਵੀਂ ਦਿੱਲੀ: ਪਿਛਲੇ ਇਕ ਦਹਾਕੇ ਵਿਚ ਲਗਭਗ 70,000 ਭਾਰਤੀਆਂ ਨੇ ਅਪਣੇ ਪਾਸਪੋਰਟ ਸਰੰਡਰ ਕੀਤੇ ਹਨ। ਇਕ ਅੰਗਰੇਜ਼ੀ ਵੈਬਸਾਈਟ ’ਤੇ ਪ੍ਰਕਾਸ਼ਤ</p>\n<p>The post <a rel=\"nofollow\" href=\"https://punjabnewsusa.com/8222/india-news/%e0%a8%87%e0%a8%95-%e0%a8%a6%e0%a8%b9%e0%a8%be%e0%a8%95%e0%a9%87-%e0%a8%9a-%e0%a8%95%e0%a8%b0%e0%a9%80%e0%a8%ac-70000-%e0%a8%ad%e0%a8%be%e0%a8%b0%e0%a8%a4%e0%a9%80%e0%a8%86%e0%a8%82/\">ਇਕ ਦਹਾਕੇ ’ਚ ਕਰੀਬ 70,000 ਭਾਰਤੀਆਂ ਨੇ ਸਰੰਡਰ ਕੀਤੇ ਅਪਣੇ ਪਾਸਪੋਰਟ</a> appeared first on <a rel=\"nofollow\" href=\"https://punjabnewsusa.com\">Punjab News USA</a>.</p>\n","PublishDate":"Tue, 27 Jun 2023 13:21:20 +00:00","Link":"https://punjabnewsusa.com/8222/india-news/%e0%a8%87%e0%a8%95-%e0%a8%a6%e0%a8%b9%e0%a8%be%e0%a8%95%e0%a9%87-%e0%a8%9a-%e0%a8%95%e0%a8%b0%e0%a9%80%e0%a8%ac-70000-%e0%a8%ad%e0%a8%be%e0%a8%b0%e0%a8%a4%e0%a9%80%e0%a8%86%e0%a8%82/"},{"Title":"ਭਾਖੜਾ ਨਹਿਰ ’ਚ ਡੁੱਬਣ ਵਾਲੀਆਂ 3 ਔਰਤਾਂ ਦੇ ਪ੍ਰਵਾਰਾਂ ਨੂੰ 2-2 ਲੱਖ ਰੁਪਏ ਸਹਾਇਤਾ ਰਾਸ਼ੀ ਦੇਣਗੇ MP ਸਿਮਰਨਜੀਤ ਮਾਨ","Content":"<p>ਲਹਿਰਾਗਾਗਾ: ਸੰਗਰੂਰ ਦੇ ਮਨਿਆਣਾ &#8216;ਚ ਟਰੈਕਟਰ ਸਮੇਤ ਨਹਿਰ &#8216;ਚ ਡੁੱਬਣ ਵਾਲੀਆਂ 3 ਔਰਤਾਂ ਦੇ ਪ੍ਰਵਾਰਾਂ ਲਈ ਸੰਗਰੂਰ ਤੋਂ ਸੰਸਦ ਮੈਂਬਰ</p>\n<p>The post <a rel=\"nofollow\" href=\"https://punjabnewsusa.com/8223/punjab-news/%e0%a8%ad%e0%a8%be%e0%a8%96%e0%a9%9c%e0%a8%be-%e0%a8%a8%e0%a8%b9%e0%a8%bf%e0%a8%b0-%e0%a8%9a-%e0%a8%a1%e0%a9%81%e0%a9%b1%e0%a8%ac%e0%a8%a3-%e0%a8%b5%e0%a8%be%e0%a8%b2%e0%a9%80%e0%a8%86/\">ਭਾਖੜਾ ਨਹਿਰ ’ਚ ਡੁੱਬਣ ਵਾਲੀਆਂ 3 ਔਰਤਾਂ ਦੇ ਪ੍ਰਵਾਰਾਂ ਨੂੰ 2-2 ਲੱਖ ਰੁਪਏ ਸਹਾਇਤਾ ਰਾਸ਼ੀ ਦੇਣਗੇ MP ਸਿਮਰਨਜੀਤ ਮਾਨ</a> appeared first on <a rel=\"nofollow\" href=\"https://punjabnewsusa.com\">Punjab News USA</a>.</p>\n","PublishDate":"Tue, 27 Jun 2023 13:20:21 +00:00","Link":"https://punjabnewsusa.com/8223/punjab-news/%e0%a8%ad%e0%a8%be%e0%a8%96%e0%a9%9c%e0%a8%be-%e0%a8%a8%e0%a8%b9%e0%a8%bf%e0%a8%b0-%e0%a8%9a-%e0%a8%a1%e0%a9%81%e0%a9%b1%e0%a8%ac%e0%a8%a3-%e0%a8%b5%e0%a8%be%e0%a8%b2%e0%a9%80%e0%a8%86/"},{"Title":"ਪ੍ਰਧਾਨ ਮੰਤਰੀ ਮੋਦੀ ਨੇ ਪੰਜ ਵੰਦੇ ਭਾਰਤ ਰੇਲ ਗੱਡੀਆਂ ਨੂੰ ਵਿਖਾਈ ਹਰੀ ਝੰਡੀ","Content":"<p>ਭੋਪਾਲ: ਪ੍ਰਧਾਨ ਮੰਤਰੀ ਨਰਿੰਦਰ ਮੋਦੀ ਨੇ ਮੰਗਲਵਾਰ ਨੂੰ ਮੱਧ ਪ੍ਰਦੇਸ਼ ਦੀ ਰਾਜਧਾਨੀ ਭੋਪਾਲ ਦਾ ਦੌਰਾ ਕੀਤਾ ਅਤੇ ਦੇਸ਼ ਦੇ ਵੱਖੋ-ਵੱਖ</p>\n<p>The post <a rel=\"nofollow\" href=\"https://punjabnewsusa.com/8217/india-news/%e0%a8%aa%e0%a9%8d%e0%a8%b0%e0%a8%a7%e0%a8%be%e0%a8%a8-%e0%a8%ae%e0%a9%b0%e0%a8%a4%e0%a8%b0%e0%a9%80-%e0%a8%ae%e0%a9%8b%e0%a8%a6%e0%a9%80-%e0%a8%a8%e0%a9%87-%e0%a8%aa%e0%a9%b0%e0%a8%9c-%e0%a8%b5/\">ਪ੍ਰਧਾਨ ਮੰਤਰੀ ਮੋਦੀ ਨੇ ਪੰਜ ਵੰਦੇ ਭਾਰਤ ਰੇਲ ਗੱਡੀਆਂ ਨੂੰ ਵਿਖਾਈ ਹਰੀ ਝੰਡੀ</a> appeared first on <a rel=\"nofollow\" href=\"https://punjabnewsusa.com\">Punjab News USA</a>.</p>\n","PublishDate":"Tue, 27 Jun 2023 13:19:33 +00:00","Link":"https://punjabnewsusa.com/8217/india-news/%e0%a8%aa%e0%a9%8d%e0%a8%b0%e0%a8%a7%e0%a8%be%e0%a8%a8-%e0%a8%ae%e0%a9%b0%e0%a8%a4%e0%a8%b0%e0%a9%80-%e0%a8%ae%e0%a9%8b%e0%a8%a6%e0%a9%80-%e0%a8%a8%e0%a9%87-%e0%a8%aa%e0%a9%b0%e0%a8%9c-%e0%a8%b5/"},{"Title":"ਹੁਣ ਤੋਂ ਪੂਰੇ ਨਾਮ ਨਾਲ ਜਾਣੀ ਜਾਵੇਗੀ ਗੁਰੂ ਅੰਗਦ ਦੇਵ ਵੈਟਰਨਰੀ ਅਤੇ ਐਨੀਮਲ ਸਾਇੰਸਜ਼ ਯੂਨੀਵਰਸਿਟੀ","Content":"<p>ਚੰਡੀਗੜ੍ਹ : ਪੰਜਾਬ ਦੇ ਪਸ਼ੂ ਪਾਲਣ, ਡੇਅਰੀ ਵਿਕਾਸ ਅਤੇ ਮੱਛੀ ਪਾਲਣ ਮੰਤਰੀ ਗੁਰਮੀਤ ਸਿੰਘ ਖੁੱਡੀਆਂ ਨੇ ਅੱਜ ਸਮੂਹ ਅਧਿਕਾਰੀਆਂ ਨੂੰ ਹਦਾਇਤ</p>\n<p>The post <a rel=\"nofollow\" href=\"https://punjabnewsusa.com/8218/top-news/%e0%a8%b9%e0%a9%81%e0%a8%a3-%e0%a8%a4%e0%a9%8b%e0%a8%82-%e0%a8%aa%e0%a9%82%e0%a8%b0%e0%a9%87-%e0%a8%a8%e0%a8%be%e0%a8%ae-%e0%a8%a8%e0%a8%be%e0%a8%b2-%e0%a8%9c%e0%a8%be%e0%a8%a3%e0%a9%80-%e0%a8%9c/\">ਹੁਣ ਤੋਂ ਪੂਰੇ ਨਾਮ ਨਾਲ ਜਾਣੀ ਜਾਵੇਗੀ ਗੁਰੂ ਅੰਗਦ ਦੇਵ ਵੈਟਰਨਰੀ ਅਤੇ ਐਨੀਮਲ ਸਾਇੰਸਜ਼ ਯੂਨੀਵਰਸਿਟੀ</a> appeared first on <a rel=\"nofollow\" href=\"https://punjabnewsusa.com\">Punjab News USA</a>.</p>\n","PublishDate":"Tue, 27 Jun 2023 13:18:30 +00:00","Link":"https://punjabnewsusa.com/8218/top-news/%e0%a8%b9%e0%a9%81%e0%a8%a3-%e0%a8%a4%e0%a9%8b%e0%a8%82-%e0%a8%aa%e0%a9%82%e0%a8%b0%e0%a9%87-%e0%a8%a8%e0%a8%be%e0%a8%ae-%e0%a8%a8%e0%a8%be%e0%a8%b2-%e0%a8%9c%e0%a8%be%e0%a8%a3%e0%a9%80-%e0%a8%9c/"},{"Title":"ਭੈਣ ਨੂੰ ਮਿਲਣ ਲਈ ਛੁੱਟੀ ‘ਤੇ ਆਏ ਫ਼ੌਜੀ ਭਰਾ ਦਾ ਗੋਲ਼ੀਆਂ ਮਾਰ ਕੇ ਕਤਲ","Content":"<p>ਜੰਡਿਆਲਾ ਗੁਰੂ : ਜੰਡਿਆਲਾ ’ਚ ਉਸ ਵੇਲੇ ਹੜਕੰਪ ਮਚ ਗਿਆ ਜਦ ਛੁੱਟੀ &#8216;ਤੇ ਆਏ ਫ਼ੌਜੀ ਦਾ ਕਤਲ ਕਰ ਦਿਤਾ ਗਿਆ।</p>\n<p>The post <a rel=\"nofollow\" href=\"https://punjabnewsusa.com/8212/punjab-news/%e0%a8%ad%e0%a9%88%e0%a8%a3-%e0%a8%a8%e0%a9%82%e0%a9%b0-%e0%a8%ae%e0%a8%bf%e0%a8%b2%e0%a8%a3-%e0%a8%b2%e0%a8%88-%e0%a8%9b%e0%a9%81%e0%a9%b1%e0%a8%9f%e0%a9%80-%e0%a8%a4%e0%a9%87-%e0%a8%86%e0%a8%8f/\">ਭੈਣ ਨੂੰ ਮਿਲਣ ਲਈ ਛੁੱਟੀ &#8216;ਤੇ ਆਏ ਫ਼ੌਜੀ ਭਰਾ ਦਾ ਗੋਲ਼ੀਆਂ ਮਾਰ ਕੇ ਕਤਲ</a> appeared first on <a rel=\"nofollow\" href=\"https://punjabnewsusa.com\">Punjab News USA</a>.</p>\n","PublishDate":"Tue, 27 Jun 2023 13:14:59 +00:00","Link":"https://punjabnewsusa.com/8212/punjab-news/%e0%a8%ad%e0%a9%88%e0%a8%a3-%e0%a8%a8%e0%a9%82%e0%a9%b0-%e0%a8%ae%e0%a8%bf%e0%a8%b2%e0%a8%a3-%e0%a8%b2%e0%a8%88-%e0%a8%9b%e0%a9%81%e0%a9%b1%e0%a8%9f%e0%a9%80-%e0%a8%a4%e0%a9%87-%e0%a8%86%e0%a8%8f/"},{"Title":"ਕਰੰਟ ਨਾਲ ਮੌਤ ਦਾ ਮਾਮਲਾ : ਐਨ.ਐਚ.ਆਰ.ਸੀ. ਨੇ ਰੇਲਵੇ ਬੋਰਡ, ਦਿੱਲੀ ਸਰਕਾਰ ਅਤੇ ਪੁਲਿਸ ਕਮਿਸ਼ਨਰ ਤੋਂ ਜਵਾਬ ਤਲਬ ਕੀਤਾ","Content":"<p>ਨਵੀਂ ਦਿੱਲੀ: ਕੌਮੀ ਮਨੁੱਖੀ ਅਧਿਕਾਰ ਕਮਿਸ਼ਨ (ਐਨ.ਐਚ.ਆਰ.ਸੀ.) ਨੇ ਨਵੀਂ ਦਿੱਲੀ ਰੇਲਵੇ ਸਟੇਸ਼ਨ ’ਤੇ ਕਰੰਟ ਲੱਗਣ ਨਾਲ ਇਕ ਔਰਤ ਦੀ ਮੌਤ</p>\n<p>The post <a rel=\"nofollow\" href=\"https://punjabnewsusa.com/8206/features-news/%e0%a8%95%e0%a8%b0%e0%a9%b0%e0%a8%9f-%e0%a8%a8%e0%a8%be%e0%a8%b2-%e0%a8%ae%e0%a9%8c%e0%a8%a4-%e0%a8%a6%e0%a8%be-%e0%a8%ae%e0%a8%be%e0%a8%ae%e0%a8%b2%e0%a8%be-%e0%a8%90%e0%a8%a8-%e0%a8%90%e0%a8%9a/\">ਕਰੰਟ ਨਾਲ ਮੌਤ ਦਾ ਮਾਮਲਾ : ਐਨ.ਐਚ.ਆਰ.ਸੀ. ਨੇ ਰੇਲਵੇ ਬੋਰਡ, ਦਿੱਲੀ ਸਰਕਾਰ ਅਤੇ ਪੁਲਿਸ ਕਮਿਸ਼ਨਰ ਤੋਂ ਜਵਾਬ ਤਲਬ ਕੀਤਾ</a> appeared first on <a rel=\"nofollow\" href=\"https://punjabnewsusa.com\">Punjab News USA</a>.</p>\n","PublishDate":"Tue, 27 Jun 2023 13:14:10 +00:00","Link":"https://punjabnewsusa.com/8206/features-news/%e0%a8%95%e0%a8%b0%e0%a9%b0%e0%a8%9f-%e0%a8%a8%e0%a8%be%e0%a8%b2-%e0%a8%ae%e0%a9%8c%e0%a8%a4-%e0%a8%a6%e0%a8%be-%e0%a8%ae%e0%a8%be%e0%a8%ae%e0%a8%b2%e0%a8%be-%e0%a8%90%e0%a8%a8-%e0%a8%90%e0%a8%9a/"},{"Title":"ਸ੍ਰੀ ਅਨੰਦਪੁਰ ਸਾਹਿਬ ਵਿਖੇ ਵਿਸ਼ਵ ਸਿੱਖ ਇਕੱਤਰਤਾ ਸ਼ੁਰੂ; ਪੰਥਕ ਰਿਵਾਇਅਤ ਅਨੁਸਾਰ ਗੁਰਮਤਾ ਸੋਧਿਆ ਜਾਵੇਗਾ","Content":"<p>ਅੱਜ ਮੀਰੀ-ਪੀਰੀ ਦਿਹਾੜਾ ਹੈ। ਛੇਵੇਂ ਸਤਿਗੁਰੂ ਤੇ ਮੀਰੀ-ਪੀਰੀ ਦੇ ਮਾਲਕ ਸਾਹਿਬ ਸ੍ਰੀ ਗੁਰੂ ਹਰਿਗੋਬਿੰਦ ਜੀ ਦੇ ਨਾਲ ਸੰਬੰਧਤ ਪਵਿੱਤਰ ਦਿਵਸ ਹੈ। ਸ੍ਰੀ ਗੁਰੂ ਹਰਿਗੋਬਿੰਦ ਜੀ ਨੇ ਅਕਾਲ ਤਖਤ ਸਾਹਿਬ ਦੀ ਸਥਾਪਨਾ ਕੀਤੀ। ਅਕਾਲ ਤਖਤ ਸਾਹਿਬ ਖਾਲਸਾ ਪੰਥ ਦੇ ਪਾਤਿਸ਼ਾਹੀ ਦਾਅਵੇ ਦਾ ਜਲੌਅ ਪਰਗਟ ਕਰਨ ਵਾਲਾ ਸ਼੍ਰੋਮਣੀ ਅਸਥਾਨ ਹੈ। ਸ੍ਰੀ ਅਕਾਲ ਤਖਤ ਸਾਹਿਬ ਵਿਖੇ ਖਾਲਸਾ ਪੰਥ ਗੁਰਮਤਾ ਕਰਕੇ ਆਪਣੇ ਸਾਂਝੇ ਫੈਸਲੇ ਲੈਂਦਾ ਰਿਹਾ ਹੈ।</p>\n<p><a rel=\"nofollow\" href=\"/sikh-news-20230628/\">ਸ੍ਰੀ ਅਨੰਦਪੁਰ ਸਾਹਿਬ ਵਿਖੇ ਵਿਸ਼ਵ ਸਿੱਖ ਇਕੱਤਰਤਾ ਸ਼ੁਰੂ; ਪੰਥਕ ਰਿਵਾਇਅਤ ਅਨੁਸਾਰ ਗੁਰਮਤਾ ਸੋਧਿਆ ਜਾਵੇਗਾ</a> appeared first on <a rel=\"nofollow\" href=\"\">Sikh Siyasat News</a>.</p>\n","PublishDate":"Wed, 28 Jun 2023 11:08:43 +00:00","Link":"/sikh-news-20230628/"},{"Title":"ਸ੍ਰੀ ਅਨੰਦਪੁਰ ਸਾਹਿਬ ਵਿਖੇ ਵਿਸ਼ਵ ਸਿੱਖ ਇਕੱਤਰਤਾ ਭਲਕੇ","Content":"<p>ਪੰਥ ਸੇਵਕ ਸਖਸ਼ੀਅਤਾਂ ਵਲੋਂ 28 ਜੂਨ ਨੂੰ ਮੀਰੀ ਪੀਰੀ ਦਿਵਸ 'ਤੇ ਸ੍ਰੀ ਅਨੰਦਪੁਰ ਸਾਹਿਬ ਵਿਖੇ ਵਿਸ਼ਵ ਸਿੱਖ ਇਕੱਤਰਤਾ ਸੱਦੀ ਗਈ ਹੈ। ਇਹਨਾਂ ਪੰਥ ਸੇਵਕ ਜੁਝਾਰੂ ਸਖਸ਼ੀਅਤਾਂ ਵਲੋਂ ਪਿਛਲੇ ਸਮੇਂ ਤੋਂ ਪੰਥ ਅੰਦਰਲੇ ਵੱਖ-ਵੱਖ ਹਿੱਸਿਆਂ ਨਾਲ ਗੋਸ਼ਟੀਆਂ ਰਚਾਈਆਂ ਗਈਆ ਅਤੇ ਵਿਚਾਰ ਵਟਾਂਦਰੇ ਕੀਤੇ ਗਏ ਸਨ।</p>\n<p><a rel=\"nofollow\" href=\"/sikh-news-20230627/\">ਸ੍ਰੀ ਅਨੰਦਪੁਰ ਸਾਹਿਬ ਵਿਖੇ ਵਿਸ਼ਵ ਸਿੱਖ ਇਕੱਤਰਤਾ ਭਲਕੇ</a> appeared first on <a rel=\"nofollow\" href=\"\">Sikh Siyasat News</a>.</p>\n","PublishDate":"Tue, 27 Jun 2023 07:15:13 +00:00","Link":"/sikh-news-20230627/"},{"Title":"ਕਾਰ ਸੇਵਾ ਖਡੂਰ ਸਾਹਿਬ ਵਾਲਿਆਂ ਦੀ ਸਰਪ੍ਰਸਤੀ ਅਧੀਨ ਸੰਗਰੂਰ ਜ਼ਿਲ੍ਹੇ ਵਿੱਚ ਲਗਾਏ ਗਏ 3 ਜੰਗਲ","Content":"<p>ਬਾਬਾ ਸੇਵਾ ਸਿੰਘ ਜੀ ਕਾਰ ਸੇਵਾ ਖਡੂਰ ਸਾਹਿਬ ਵਾਲਿਆਂ ਦੀ ਸਰਪ੍ਰਸਤੀ ਅਧੀਨ ਨਿਸ਼ਾਨ-ਏ-ਸਿੱਖੀ ਕਾਰ ਸੇਵਾ ਖਡੂਰ ਸਾਹਿਬ ਵੱਲੋਂ ਵਾਤਾਵਰਣ ਦੀ ਸਾਂਭ ਸੰਭਾਲ ਮਹਿੰਮ ਸ਼ੁਰੂ ਕੀਤੀ ਗਈ ਹੈ।</p>\n<p><a rel=\"nofollow\" href=\"/forests-planted-in-sangrur-district/\">ਕਾਰ ਸੇਵਾ ਖਡੂਰ ਸਾਹਿਬ ਵਾਲਿਆਂ ਦੀ ਸਰਪ੍ਰਸਤੀ ਅਧੀਨ ਸੰਗਰੂਰ ਜ਼ਿਲ੍ਹੇ ਵਿੱਚ ਲਗਾਏ ਗਏ 3 ਜੰਗਲ</a> appeared first on <a rel=\"nofollow\" href=\"\">Sikh Siyasat News</a>.</p>\n","PublishDate":"Mon, 26 Jun 2023 11:15:21 +00:00","Link":"/forests-planted-in-sangrur-district/"},{"Title":"ਵਿਸ਼ਵ ਸਿੱਖ ਇਕੱਤਰਤਾ ਵਿਚ ਗੁਰਮਤੇ ਦੀ ਵਿਧੀ ਰਾਹੀਂ ਲਿਆ ਜਾਵੇਗਾ ਸਾਂਝਾ ਫੈਸਲਾ: ਪੰਥ ਸੇਵਕ ਸ਼ਖ਼ਸੀਅਤਾਂ","Content":"<p>ਪੰਥ ਸੇਵਕ ਸਖਸ਼ੀਅਤਾਂ ਭਾਈ ਦਲਜੀਤ ਸਿੰਘ ਬਿੱਟੂ, ਭਾਈ ਨਰਾਇਣ ਸਿੰਘ, ਭਾਈ ਸਤਨਾਮ ਸਿੰਘ ਖੰਡੇਵਾਲਾ ਅਤੇ ਭਾਈ ਸਤਨਾਮ ਸਿੰਘ ਝੰਜੀਆਂ ਨੇ ਅੱਜ ਇਥੇ ਅੰਮ੍ਰਿਤਸਰ ਵਿਖੇ ਇਕ ਪੱਤਰਕਾਰ ਵਾਰਤਾ ਦੌਰਾਨ ਮੀਰੀ ਪੀਰੀ ਦਿਵਸ ਮੌਕੇ ਹੋਣ ਵਾਲੀ ਵਿਸ਼ਵ ਸਿੱਖ ਇਕੱਤਰਤਾ ਬਾਰੇ ਜਾਣਕਾਰੀ ਸਾਂਝੀ ਕੀਤੀ।</p>\n<p><a rel=\"nofollow\" href=\"/sikh-news-20230626/\">ਵਿਸ਼ਵ ਸਿੱਖ ਇਕੱਤਰਤਾ ਵਿਚ ਗੁਰਮਤੇ ਦੀ ਵਿਧੀ ਰਾਹੀਂ ਲਿਆ ਜਾਵੇਗਾ ਸਾਂਝਾ ਫੈਸਲਾ: ਪੰਥ ਸੇਵਕ ਸ਼ਖ਼ਸੀਅਤਾਂ</a> appeared first on <a rel=\"nofollow\" href=\"\">Sikh Siyasat News</a>.</p>\n","PublishDate":"Mon, 26 Jun 2023 09:23:22 +00:00","Link":"/sikh-news-20230626/"},{"Title":"ਅਮਰੀਕਾ ਫੇਰੀ ਦੌਰਾਨ ਪ੍ਰਧਾਨ ਮੰਤਰੀ ਮੋਦੀ ਦਾ ਵੱਖ-ਵੱਖ ਜਥੇਬੰਦੀਆਂ ਵੱਲੋਂ ਵਿਰੋਧ","Content":"<p>ਬੀਤੇ ਦਿਨੀਂ ਪ੍ਰਧਾਨ ਮੰਤਰੀ ਨਰਿੰਦਰ ਮੋਦੀ ਦੀ ਅਮਰੀਕਾ ਫੇਰੀ ਦੌਰਾਨ ਜਦੋਂ ਪ੍ਰਧਾਨ ਮੰਤਰੀ ਅਮਰੀਕਾ ਦੀ ਰਾਜਧਾਨੀ ਵਿਖ਼ੇ ਵ੍ਹਾਈਟ ਹਾਊਸ ਪੁੱਜੇ ਤਾ ਮਣੀਪੁਰ, ਪੰਜਾਬ, ਕਸ਼ਮੀਰ, ਨਾਗਾਲੈਂਡ, ਦਲਿਤ, ਈਸਾਈ ਭਾਈਚਾਰੇ ਦੇ ਲੋਕਾਂ ਦੇ ਵੱਡੇ ਇਕੱਠੇ ਨੇ ਪ੍ਰਧਾਨ ਮੰਤਰੀ ਦਾ ਸਖ਼ਤ ਵਿਰੋਧ ਕੀਤਾ ।</p>\n<p><a rel=\"nofollow\" href=\"/sikh-news-20230624/\">ਅਮਰੀਕਾ ਫੇਰੀ ਦੌਰਾਨ ਪ੍ਰਧਾਨ ਮੰਤਰੀ ਮੋਦੀ ਦਾ ਵੱਖ-ਵੱਖ ਜਥੇਬੰਦੀਆਂ ਵੱਲੋਂ ਵਿਰੋਧ</a> appeared first on <a rel=\"nofollow\" href=\"\">Sikh Siyasat News</a>.</p>\n","PublishDate":"Sat, 24 Jun 2023 11:09:34 +00:00","Link":"/sikh-news-20230624/"},{"Title":"ਵਿਸ਼ਵ ਸਿੱਖ ਇਕੱਤਰਤਾ : ਵਿੰਡਸਰ (ਕਨੇਡਾ) ਦੀਆਂ ਸੰਗਤਾਂ ਵੱਲੋਂ ਸਮੂਹ ਪੰਥ ਨੂੰ ਅਪੀਲ","Content":"<p>ਪੰਥ ਸੇਵਕਾਂ ਵੱਲੋਂ ਸਾਰੇ ਵਿਸ਼ਵ ਦੇ ਸਿੱਖਾਂ ਦੇ ਸਹਿਯੋਗ ਨਾਲ ਵਿਸ਼ਵ ਸਿੱਖ ਇਕੱਤਰਤਾ ਸ੍ਰੀ ਅਨੰਦਪੁਰ ਸਾਹਿਬ ਵਿਖੇ ੨੮ ਜੂਨ ੨੦੨੩ ਨੂੰ ਸੱਦੀ ਗਈ ਹੈ।</p>\n<p><a rel=\"nofollow\" href=\"/world-sikh-gathering/\">ਵਿਸ਼ਵ ਸਿੱਖ ਇਕੱਤਰਤਾ : ਵਿੰਡਸਰ (ਕਨੇਡਾ) ਦੀਆਂ ਸੰਗਤਾਂ ਵੱਲੋਂ ਸਮੂਹ ਪੰਥ ਨੂੰ ਅਪੀਲ</a> appeared first on <a rel=\"nofollow\" href=\"\">Sikh Siyasat News</a>.</p>\n","PublishDate":"Sat, 24 Jun 2023 06:08:44 +00:00","Link":"/world-sikh-gathering/"},{"Title":"ਗੁਰਬਾਣੀ ਪ੍ਰਸਾਰਣ ਮਸਲਾ: ਪੰਥ ਸੇਵਕ ਸ਼ਖ਼ਸੀਅਤਾਂ ਨੇ ਸਰਕਾਰ ਤੇ ਸ਼੍ਰੋਮਣੀ ਕਮੇਟੀ ਦੋਹਾਂ ਨੂੰ ਗਲਤ ਕਰਾਰ ਦਿੱਤਾ","Content":"<p>ਪੰਥ ਸੇਵਕ ਜੁਝਾਰੂ ਸ਼ਖ਼ਸੀਅਤਾਂ ਨੇ ਅੱਜ ਜਾਰੀ ਇਕ ਸਾਂਝੇ ਬਿਆਨ ਰਾਹੀਂ ਕਿਹਾ ਹੈ ਕਿ ਗੁਰਦੁਆਰਾ ਐਕਟ ਵਿੱਚ ਤਰਮੀਮ ਭਗਵੰਤ ਮਾਨ ਸਰਕਾਰ ਦਾ ਸਿੱਖਾਂ ਦੇ ਧਾਰਮਿਕ ਮਾਲਿਆਂ ਵਿੱਚ ਦਖ਼ਲ ਹੈ। ਉਹਨਾ ਕਿਹਾ ਕਿ ਦੂਜੇ ਪਾਸੇ ਸ਼੍ਰੋਮਣੀ ਕਮੇਟੀ ਵੱਲੋਂ ਕੀਰਤਨ ਪ੍ਰਸਾਰਨ ਲਈ ਟੈਂਡਰਾਂ ਦੀ ਗੱਲ ਬਾਦਲ ਪਰਿਵਾਰ ਨੂੰ ਲਾਹਾ ਦਿਵਾਉਣ ਵਾਲੀ ਗੁਰਮਤਿ ਵਿਰੋਧੀ ਸੋਚ ਹੈ।</p>\n<p><a rel=\"nofollow\" href=\"/joint-statement-of-sikh-leader-15/\">ਗੁਰਬਾਣੀ ਪ੍ਰਸਾਰਣ ਮਸਲਾ: ਪੰਥ ਸੇਵਕ ਸ਼ਖ਼ਸੀਅਤਾਂ ਨੇ ਸਰਕਾਰ ਤੇ ਸ਼੍ਰੋਮਣੀ ਕਮੇਟੀ ਦੋਹਾਂ ਨੂੰ ਗਲਤ ਕਰਾਰ ਦਿੱਤਾ</a> appeared first on <a rel=\"nofollow\" href=\"\">Sikh Siyasat News</a>.</p>\n","PublishDate":"Thu, 22 Jun 2023 12:07:53 +00:00","Link":"/joint-statement-of-sikh-leader-15/"},{"Title":"ਭਾਈ ਹਰਦੀਪ ਸਿੰਘ ਨਿੱਝਰ ਦੇ ਕਨੇਡਾ ਵਿਚ ਕਤਲ ਬਾਰੇ ਦਲ ਖਾਲਸਾ ਦਾ ਪ੍ਰਤੀਕਰਮ","Content":"<p>ਦਲ ਖ਼ਾਲਸਾ ਨੇ ਭਾਈ ਹਰਦੀਪ ਸਿੰਘ ਨਿੱਝਰ ਦੇ ਕਤਲ ਦੀ ਖਬਰ ਉਤੇ ਤਿੱਖਾ ਪ੍ਰਤੀਕਰਮ ਦੇਂਦਿਆਂ ਕਿਹਾ ਕਿ ਪੰਥ ਦੇ ਦੁਸ਼ਮਣਾਂ ਨੇ ਭਾਉ ਪਰਮਜੀਤ ਸਿੰਘ ਪੰਜਵੜ ਤੋਂ ਬਾਅਦ ਖ਼ਾਲਿਸਤਾਨ ਦੇ ਸੰਘਰਸ਼ ਦਾ ਇਕ ਹੋਰ ਕੀਮਤੀ ਹੀਰਾ ਸਾਥੋਂ ਖੋਹ ਲਿਆ ਹੈ।</p>\n<p><a rel=\"nofollow\" href=\"/sikh-news-20230620-3/\">ਭਾਈ ਹਰਦੀਪ ਸਿੰਘ ਨਿੱਝਰ ਦੇ ਕਨੇਡਾ ਵਿਚ ਕਤਲ ਬਾਰੇ ਦਲ ਖਾਲਸਾ ਦਾ ਪ੍ਰਤੀਕਰਮ</a> appeared first on <a rel=\"nofollow\" href=\"\">Sikh Siyasat News</a>.</p>\n","PublishDate":"Tue, 20 Jun 2023 10:29:48 +00:00","Link":"/sikh-news-20230620-3/"},{"Title":"ਏਜੀਪੀਸੀ ਨੇ ਹਰਦੀਪ ਸਿੰਘ ਨਿੱਝਰ ਦੇ ਕਤਲ ਨੂੰ ਭਾਰਤੀ ਮੰਨੂਵਾਦੀ ਅੱਤਵਾਦ ਨਾਲ ਜੋੜਿਆ","Content":"<p>ਅਮਰੀਕਨ ਗੁਰਦੁਆਰਾ ਪ੍ਰਬੰਧਕ ਕਮੇਟੀ ਵੱਲੋਂ ਭਾਈ ਨਿੱਝਰ ਦੇ ਕਤਲ ਨੂੰ ਭਾਰਤ ਸਰਕਾਰ ਦੁਆਰਾ ਸਿੱਖਾਂ ਦੀ ਨਸਲਕੁਸ਼ੀ ਕਰਾਰ ਦਿੱਤਾ ਹੈ। ਕਮੇਟੀ ਦੇ ਕੋਆਰਡੀਨੇਟਰ ਡਾ: ਪ੍ਰਿਤਪਾਲ ਸਿੰਘ ਹੁਰਾਂ ਪ੍ਰੈਸ ਦੇ ਨਾਮ ਜਾਰੀ ਬਿਆਨ ਵਿੱਚ ਕਿਹਾ ਹੈ ਕਿ ਗੈਂਗਾਂ ਨੂੰ ਰਕਮਾਂ ਦੇ ਕੇ ਸੋਸ਼ਲ ਮੀਡੀਏ ਉਤੇ ਸਿੱਖ ਆਗੂਆਂ ਦੇ ਕਤਲ ਕਰਵਾਉਣ ਦੀਆਂ ਜ਼ਿਮੇਵਾਰੀਆਂ ਲੈਣ ਨੂੰ ਸਰਕਾਰੀ ਅੱਤਵਾਦ ਕਿਹਾ ਜਾ ਸਕਦਾ ਹੈ</p>\n<p><a rel=\"nofollow\" href=\"/sikh-news-20230620-2/\">ਏਜੀਪੀਸੀ ਨੇ ਹਰਦੀਪ ਸਿੰਘ ਨਿੱਝਰ ਦੇ ਕਤਲ ਨੂੰ ਭਾਰਤੀ ਮੰਨੂਵਾਦੀ ਅੱਤਵਾਦ ਨਾਲ ਜੋੜਿਆ</a> appeared first on <a rel=\"nofollow\" href=\"\">Sikh Siyasat News</a>.</p>\n","PublishDate":"Tue, 20 Jun 2023 09:12:40 +00:00","Link":"/sikh-news-20230620-2/"},{"Title":"ਹਰਦੀਪ ਸਿੰਘ ਨਿੱਝਰ ਨੂੰ ਸ਼ਹੀਦ ਕਰਨਾ ਸਿੱਖਾਂ ਦੀ ਅਵਾਜ਼ ਦਬਾਉਣ ਦਾ ਯਤਨ: ਪੰਥ ਸੇਵਕ","Content":"<p>ਥ ਸੇਵਕ ਜੁਝਾਰੂ ਸ਼ਖ਼ਸੀਅਤਾਂ ਨੇ ਜਾਰੀ ਇਕ ਸਾਂਝੇ ਬਿਆਨ ਵਿਚ ਕਿਹਾ ਹੈ ਕਿ ਕਨੇਡਾ ਦੇ ਸ਼ਹਿਰ ਸਰੀ ਵਿਚ ਗੁਰੂ ਨਾਨਕ ਸਿੱਖ ਗੁਰਦੁਆਰਾ ਸਾਹਿਬ ਦੀ ਪ੍ਰਬੰਧਕ ਕਮੇਟੀ ਦੇ ਮੁਖੀ ਭਾਈ ਹਰਦੀਪ ਸਿੰਘ ਨਿੱਝਰ ਨੂੰ ਹਥਿਆਰਬੰਦ ਹਮਲਾਵਰਾਂ ਨੇ ਸ਼ਹੀਦ ਕਰਕੇ ਸਿੱਖਾਂ ਦੀ ਹੱਕ, ਸੱਚ ਤੇ ਆਜ਼ਾਦੀ ਦੀ ਆਵਾਜ਼ ਨੂੰ ਦਬਾਉਣ ਦਾ ਯਤਨ ਕੀਤਾ ਹੈ।</p>\n<p><a rel=\"nofollow\" href=\"/sikh-news-20230620/\">ਹਰਦੀਪ ਸਿੰਘ ਨਿੱਝਰ ਨੂੰ ਸ਼ਹੀਦ ਕਰਨਾ ਸਿੱਖਾਂ ਦੀ ਅਵਾਜ਼ ਦਬਾਉਣ ਦਾ ਯਤਨ: ਪੰਥ ਸੇਵਕ</a> appeared first on <a rel=\"nofollow\" href=\"\">Sikh Siyasat News</a>.</p>\n","PublishDate":"Tue, 20 Jun 2023 05:05:09 +00:00","Link":"/sikh-news-20230620/"}]