[{"Title":"ਮੇਰਠ 'ਚ ਪੁਲਿਸ 'ਤੇ ਪਥਰਾਅ, ਸਿਟੀ ਮਜਿਸਟ੍ਰੇਟ-ਦਰੋਗਾ ਜ਼ਖ਼ਮੀ","Content":" ਕੋਰੋਨਾ ਇਨਫੈਕਸ਼ਨ ਤੋਂ ਬਚਾਅ ਲਈ ਮੇਰਠ ਦੇ ਜਲੀ ਕੋਠੀ ਖੇਤਰ ਨੂੰ ਸੀਲ ਕਰਨ ਗਈ ਪੁਲਿਸ-ਪ੍ਰਸਾਸਨ ਦੀ ਟੀਮ 'ਤੇ ਦਰੀ ਮਸਜਿਦ ਨੇੜੇ ਭੀੜ ਨੇ ਪਥਰਾਅ ਕਰ ਦਿੱਤਾ। ਸਿਟੀ ਮੈਜਿਸਟ੍ਰੇਟ ਤੇ ਇਕ ਦਰੋਗਾ ਜ਼ਖ਼ਮੀ ਹੋ ਗਏ। ","PublishDate":"Sat, 11 Apr 2020 16:35:30 +00:00","Link":"https://punjabi.jagran.com/national/general-police-magistrate-city-magistrate-injured-in-meerut-8769557.html"},{"Title":"ਹੁਕਮਾਂ ਦੀ ਉਲੰਘਣਾ 'ਤੇ ਬੀਡੀਪੀਓ ਗਿ੍ਫ਼ਤਾਰ","Content":"ਸ਼ਾਮ ਸਿੰਘ ਘੁੰਮਣ, ਦੀਨਾਨਗਰ : ਕੋਰੋਨਾ ਵਾਇਰਸ ਦੇ ਸੰਕਟ ਦੌਰਾਨ ਜ਼ਰੂਰਤਮੰਦ ਗਰੀਬ ਪਰਿਵਾਰਾਂ ਨੂੰ ਰਾਸ਼ਨ ਵੰਡਣ ਸਬੰਧੀ ਰਿਪੋਰਟ ਉੱਚ ਪ੍ਰਸਾਸ਼ਨਿਕ ਅਧਿਕਾਰੀਆਂ ਨੂੰ ਨਾ ਦੇਣ ਦੇ ਦੋਸ਼ਾਂ ਹੇਠ ਦੀਨਾਨਗਰ ਪੁਲਿਸ ਨੇ ਬੀਡੀਪੀਓ ਗੁਰਦਾਸਪੁਰ ਨੂੰ ਮਾਮਲਾ ਦਰਜ ਕਰ ਕੇ ਗਿ੍ਫਤਾਰ ਕਰ ਲਿਆ ਹੈ।","PublishDate":"Sat, 11 Apr 2020 16:34:13 +00:00","Link":"https://punjabi.jagran.com/national/general-bdpo-arrest-violations-of-govt-orders-8769565.html"},{"Title":"ਅਮਰੀਕਾ 'ਚ ਭਾਰਤੀਆਂ ਨੇ ਐੱਚ-1ਬੀ ਵੀਜ਼ਾ ਵਧਾਉਣ ਲਈ ਕਿਹਾ","Content":" ਕੋਰੋਨਾ ਮਹਾਮਾਰੀ ਦੇ ਖ਼ਤਮ ਹੋਣ ਤਕ ਭਾਰਤ ਨੇ ਆਪਣੇ ਨਾਗਰਿਕਾਂ ਦੇ ਐੱਚ-1ਬੀ ਤੇ ਬਾਕੀ ਵੀਜ਼ਾ ਦੀ ਮਿਆਦ ਵਧਾਉਣ ਲਈ ਅਮਰੀਕਾ ਨੂੰ ਕਿਹਾ ਹੈ। ਸੂਤਰਾਂ ਮੁਤਾਬਕ ਨਵੀਂ ਦਿੱਲੀ ਨੇ ਵਾਸ਼ਿੰਗਟਨ ਨੂੰ ਇਹ ਬੇਨਤੀ ਉਦੋਂ ਕੀਤੀ ਹੈ ਜਦੋਂ ਉਸ ਨੂੰ ਇਹ ਜਾਣਕਾਰੀ ਮਿਲੀ ਕਿ ਅਮਰੀਕਾ ਸਰਕਾਰ ਨੇ ਕੰਪਨੀਆਂ ਦੇ ਐੱਚ-1ਬੀ ਵੀਜ਼ਾ ਵਾਲੇ ਪੇਸ਼ਵਰਾਂ ਦੀਆਂ ਸੇਵਾਵਾਂ ਖਤਮ ਕਰਨ ਲਈ ਕਿਹਾ ਹੈ।","PublishDate":"Sat, 11 Apr 2020 16:32:49 +00:00","Link":"https://punjabi.jagran.com/world/usa-indians-in-the-us-ask-to-increase-h1b-visa-8769564.html"},{"Title":"ਵਾਹਗਿਓਂ ਪਾਰ : ਟਿਕਟਾਕ ਰਾਹੀਂ ਉੱਡ ਰਹੀਆਂ ਕੋੋਰੋਨਾ ਪ੍ਰਬੰਧਾਂ ਦੀਆਂ ਧੱਜੀਆਂ","Content":"ਵਿਸ਼ਵ ਪੱਧਰੀ ਮਹਾਮਾਰੀ ਕੋਰੋਨਾ ਵਾਇਰਸ ਦਾ ਕਹਿਰ ਪਾਕਿਸਤਾਨ ਵਿਚ ਰੋਜ਼ਾਨਾ ਵੱਧਦਾ ਹੀ ਜਾ ਰਿਹਾ ਹੈ। ਪਾਕਿਸਤਾਨ ਵਿਚ ਹੁਣ ਤਕ ਕਰੀਬ 4,800 ਕੋਰੋਨਾ ਪ੍ਰਭਾਵਿਤ ਲੋਕਾਂ ਦਾ ਪਤਾ ਚੱਲਿਆ ਹੈ। ਉੱਥੇ ਭਾਰਤ ਵਾਂਗ ਹੀ ਕੋਰੋਨਾ ਫੈਲਾਉਣ 'ਚ ਤਬਲੀਗੀ ਜਮਾਤ ਦੇ ਸਮਾਗਮਾਂ ਦਾ ਕਾਫ਼ੀ ਹੱਥ ਹੈ। ","PublishDate":"Sat, 11 Apr 2020 16:24:37 +00:00","Link":"https://punjabi.jagran.com/world/pakistan-wahgion-paar-corona-arrivals-fleeing-by-ticket-8769315.html"},{"Title":"ਮੋਹਾਲੀ ਜ਼ਿਲ੍ਹੇ 'ਚ ਪਾਜ਼ੇਟਿਵ ਮਰੀਜ਼ਾਂ ਦੀ ਗਿਣਤੀ 50 'ਤੇ ਪੁੱਜੀ","Content":"ਸਤਵਿੰਦਰ ਸਿੰਘ ਧੜਾਕ, ਐੱਸਏਐੱਸ ਨਗਰ : ਮੋਹਾਲੀ ਜ਼ਿਲ੍ਹੇ ਵਿਚ ਕੋਰੋਨਾ ਵਾਇਰਸ ਨਾਲ ਪੀੜਤ ਮਰੀਜ਼ਾਂ ਦੀ ਗਿਣਤੀ 50 ਹੋ ਗਈ ਹੈ। ਰੋਗ ਦਾ ਕੇਂਦਰ ਪਿੰਡ ਜਵਾਹਰਪੁਰ ਹੀ ਹੈ। ਸ਼ਨਿੱਚਰਵਾਰ ਨੂੰ ਪੀਜੀਆਈ ਚੰਡੀਗੜ੍ਹ ਨੇ ਦੁਪਹਿਰੇ ਇਸੇ ਪਿੰਡ ਦੇ ਦੋ ਹੋਰ ਵਿਅਕਤੀਆਂ ਨੂੰ ਕੋਰੋਨਾ ਪੌਜ਼ਿਟਿਵ ਐਲਾਨ ਕਰ ਦਿੱਤਾ ਹੈ।\nਦੋਵੇਂ ਮਰੀਜ਼ਾਂ ਦੀ ਪਛਾਣ ਮਨਪ੍ਰਰੀਤ ਤੇ ਜਸਪਾਲ ਸਿੰਘ ਵਜੋਂ ਹੋਈ ਹੈ, ਜਿਨ੍ਹਾਂ ਦੀ ਉਮਰ 38 ਤੇ 58 ਸਾਲ ਹੈ। ਇਨ੍ਹਾਂ ਦੀਆਂ ਰਿਪੋਰਟਾਂ ਪੌਜ਼ਿਟਿਵ ਮਿਲਣ ਤੋਂ ਬਾਅਦ ਪਿੰਡ ਜਵਾਹਰਪੁਰ ਵਿਚ ਕੋਰੋਨਾ ਪੌਜ਼ਿਟਿਵ ਮਰੀਜ਼ਾਂ ਦੀ ਗਿਣਤੀ ਵੱਧ ਕੇ 34 ਹੋ ਗਈ ਹੈ। ਮਰੀਜ਼ਾਂ ਦੀ ਵੱਧ ਰਹੀ ਗਿਣਤੀ ਤੋਂ ਬਾਅਦ ਸਿਹਤ ਵਿਭਾਗ ਨੇ ਸੈਂਪਿਲੰਗ ","PublishDate":"Sat, 11 Apr 2020 16:17:02 +00:00","Link":"https://punjabi.jagran.com/punjab/chandigarh-corona-positive-case-8769455.html"},{"Title":"ਕੋਰੋਨਾ ਨਾਲ ਮੁਕਾਬਲੇ ਲਈ ਦੋ ਹਫਤੇ ਹੋਰ ਵਧੇਗਾ ਲਾਕਡਾਊਨ","Content":"ਜਾਗਰਣ ਬਿਊਰੋ, ਨਵੀਂ ਦਿੱਲੀ\nਕੋਰੋਨਾ ਵਾਇਰਸ ਮਹਾਮਾਰੀ ਦੇ ਮਹਾਸੰਕਟ ਨੂੰ ਰੋਕਣ ਲਈ 14 ਅਪ੍ਰਰੈਲ ਤਕ ਲਾਗੂ ਮੌਜੂਦਾ ਦੇਸ਼ ਪੱਧਰੀ ਲਾਕਡਾਊਨ ਦਾ ਦੋ ਹਫਤੇ ਹੋਰ ਵਧਣਾ ਤੈਅ ਹੋ ਗਿਆ ਹੈ। ਪ੍ਰਧਾਨ ਮੰਤਰੀ ਨਰਿੰਦਰ ਮੋਦੀ ਦੇ ਨਾਲ ਵੀਡੀਓ ਕਾਨਫਰੰਸਿੰਗ 'ਚ ਸਾਰੇ ਸੂਬਿਆਂ ਦੇ ਮੁੱਖ ਮੰਤਰੀਆਂ ਨੇ ਲਾਕਡਾਊਨ ਵਧਾਉਣ ਦੀ ਮੰਗ ਕੀਤੀ।","PublishDate":"Sat, 11 Apr 2020 16:16:53 +00:00","Link":"https://punjabi.jagran.com/national/general-lockdon-extended-two-more-weeks-8769563.html"},{"Title":"ਫਿਲਮਾਂ ਦੇਖ ਕੇ ਤੇ ਪਹੇਲੀਆਂ ਸੁਲਝਾ ਕੇ ਸਮਾਂ ਬਿਤਾ ਰਹੇ ਜੌਨਸਨ","Content":"ਕੋਰੋਨਾ ਵਾਇਰਸ ਤੋਂ ਪ੍ਰਭਾਵਿਤ ਬਿ੍ਟੇਨ ਦੇ ਪ੍ਰਧਾਨ ਮੰਤਰੀ ਬੋਰਿਸ ਜੌਨਸਨ ਦੀ ਹਾਲਤ ਵਿਚ ਹੁਣ ਸੁਧਾਰ ਹੋ ਰਿਹਾ ਹੈ। ਉਹ ਉੱਥੇ ਇਕ ਹਸਪਤਾਲ ਦੇ ਬਾਗ 'ਚ ਸੈਰ ਕਰ ਕੇ, ਫਿਲਮਾਂ ਦੇਖ ਕੇ, ਸੁਡੋਕੋ ਖੇਡ ਕੇ ਅਤੇ ਪਹੇਲੀਆਂ ਸੁਲਝਾ ਕੇ ਸਮਾਂ ਬਿਤਾ ਰਹੇ ਹਨ। ","PublishDate":"Sat, 11 Apr 2020 16:16:48 +00:00","Link":"https://punjabi.jagran.com/world/uk-johnson-spent-time-watching-movies-and-solving-puzzles-8769417.html"},{"Title":"ਵੈਂਟੀਲੇਟਰ ਮਿਲਣ 'ਚ ਦੇਰੀ ਨਾਲ ਗਈ ਚੀਨ 'ਚ ਜ਼ਿਆਦਾ ਲੋਕਾਂ ਦੀ ਜਾਨ","Content":" ਚੀਨ ਵਿਚ ਵੈਂਟੀਲੇਟਰ ਮਿਲਣ 'ਚ ਦੇਰੀ ਕਾਰਨ ਬਹੁਤ ਸਾਰੇ ਕੋਰੋਨਾ ਪੀੜਤਾਂ ਨੇ ਆਪਣੀ ਜਾਨ ਗੁਆਈ। ਇਕ ਅਧਿਐਨ ਮੁਤਾਬਕ ਚੀਨ 'ਚ ਕੋਰੋਨਾ ਮਹਾਮਾਰੀ ਕਾਰਨ ਮਰਨ ਵਾਲੇ ਸਿਰਫ 20 ਫੀਸਦੀ ਲੋਕਾਂ ਨੂੰ ਮਕੈਨੀਕਲ ਵੈਂਟੀਲੇਟਰ ਦੀ ਸਹੂਲਤ ਮਿਲ ਸਕੀ। ","PublishDate":"Sat, 11 Apr 2020 16:14:24 +00:00","Link":"https://punjabi.jagran.com/world/other-country-delay-in-getting-ventilators-leads-to-more-lives-in-china-8769527.html"},{"Title":"Corona Updats :ਐੱਲਪੀਯੂ ਦੀ ਵਿਦਿਆਰਥਣ ਵੀ ਕੋਰੋਨਾ ਪਾਜ਼ੇਟਿਵ,ਜਲੰਧਰ ਦੇ ਕਾਂਗਰਸੀ ਆਗੂ ਤੇ ਪਤਨੀ-ਪੁੱਤਰ ਸਮੇਤ ਸੂਬੇ 'ਚ ਨੌ ਹੋਰ ਪਾਜ਼ੇਟਿਵ","Content":"ਪੰਜਾਬ 'ਚ ਸ਼ਨਿਚਰਵਾਰ ਨੂੰ ਕੋਰੋਨਾ ਪਾਜ਼ੇਟਿਵ ਮਰੀਜ਼ਾਂ ਦਾ ਅੰਕੜਾ 160 ਤਕ ਪਹੁੰਚ ਗਿਆ। ਇਨ੍ਹਾਂ 'ਚ ਤਿੰਨ ਕੇਸ ਜਲੰਧਰ ਤੇ ਦੋ ਮੋਹਾਲੀ ਦੇ ਹਨ। ","PublishDate":"Sat, 11 Apr 2020 16:11:32 +00:00","Link":"https://punjabi.jagran.com/punjab/jalandhar-lpu-student-corona-positive-8769474.html"},{"Title":"Coronavirus : ਹੁਣ ਰੇਡੀਓ 'ਤੇ ਲੱਗਣਗੀਆਂ ਸਰਕਾਰੀ ਸਕੂਲ ਦੀਆਂ ਜਮਾਤਾਂ","Content":"ਕੋਰੋਨਾ ਵਾਇਰਸ ਕਰਕੇ ਲਾਕਡਾਊਨ ਤੇ ਕਰਫਿਊ ਦੇ ਚੱਲਦਿਆਂ ਵਿਦਿਆਰਥੀਆਂ ਦੀ ਪੜ੍ਹਾਈ ਦੇ ਹੋ ਰਹੇ ਨੁਕਸਾਨ ਨੂੰ ਪੂਰਾ ਕਰਨ ਲਈ ਜਿਥੇ ਸਕੂਲਾਂ ਤੇ ਯੂਨੀਵਰਸਿਟੀਆਂ ਵੱਲੋਂ ਆਨਲਾਈਨ ਪੜ੍ਹਾਈ ਸ਼ੁਰੂ ਕਰਵਾਈ ਗਈ ਹੈ, ਉਥੇ ਹੀ ਹੁਣ ਸਰਕਾਰੀ ਸਕੂਲਾਂ ਦੇ ਵਿਦਿਆਰਥੀਆਂ ਦੀਆਂ ਜਮਾਤਾਂ ਰੇਡੀਓ 'ਤੇ ਵੀ ਲਗਾਉਣ ਦਾ ਫ਼ੈਸਲਾ ਲਿਆ ਗਿਆ ਹੈ। ","PublishDate":"Sat, 11 Apr 2020 16:09:29 +00:00","Link":"https://punjabi.jagran.com/punjab/patiala-classrooms-on-radio-8769462.html"},{"Title":"ਸਾਬਕਾ ਸਿੱਖ ਫ਼ੌਜੀ ਨੇ ਲੋਕਾਂ ਦੀ ਭਲਾਈ ਲਈ ਦਾਨ ਕੀਤੇ ਪੈਨਸ਼ਨ ਦੇ ਜੋੜੇ 15 ਲੱਖ ਰੁਪਏ","Content":"ਮੇਰਠ- ਕੋਰੋਨਾ ਵਾਇਰਸ ਨਾਲ ਲੜਨ ਲਈ ਸੈਨਾ ਤੋਂ ਸੇਵਾਮੁਕਤ ਜੂਨੀਅਰ ਕਮਿਸ਼ਨਡ ਅਫਸਰ (ਜੇ.ਸੀ.ਓ.) ਮਹਿੰਦਰ ਸਿੰਘ ਨੇ ਪ੍ਰਧਾਨ ਮੰਤਰੀ ਰਾਹਤ ਫੰਡ","PublishDate":"Fri, 10 Apr 2020 06:15:04 +00:00","Link":"http://punjabnewsusa.com/india/%e0%a8%b8%e0%a8%be%e0%a8%ac%e0%a8%95%e0%a8%be-%e0%a8%b8%e0%a8%bf%e0%a9%b1%e0%a8%96-%e0%a9%9e%e0%a9%8c%e0%a8%9c%e0%a9%80-%e0%a8%a8%e0%a9%87-%e0%a8%b2%e0%a9%8b%e0%a8%95%e0%a8%be%e0%a8%82-%e0%a8%a6/"},{"Title":"ਕੋਰੋਨਾ ਵਾਇਰਸ: ਪੰਜਾਬ ਵਿਚ 1 ਮਿਲੀਅਨ ਲੋਕਾਂ ਦੀ ਹੋਵੇਗੀ ਸਕ੍ਰੀਨਿੰਗ","Content":"ਚੰਡੀਗੜ੍ਹ: ਪੰਜਾਬ ਦੇ ਸਿਹਤ ਮੰਤਰੀ ਬਲਬੀਰ ਸਿੰਘ ਸਿੱਧੂ ਨੇ ਵੀਰਵਾਰ ਨੂੰ ਇਕ ਲੱਖ ਲੋਕਾਂ ਦੀ ਜਾਂਚ ਲਈ ਪੰਜਾਬ ਵਿਚ ਤੇਜ਼ੀ","PublishDate":"Fri, 10 Apr 2020 06:13:29 +00:00","Link":"http://punjabnewsusa.com/featured/%e0%a8%95%e0%a9%8b%e0%a8%b0%e0%a9%8b%e0%a8%a8%e0%a8%be-%e0%a8%b5%e0%a8%be%e0%a8%87%e0%a8%b0%e0%a8%b8-%e0%a8%aa%e0%a9%b0%e0%a8%9c%e0%a8%be%e0%a8%ac-%e0%a8%b5%e0%a8%bf%e0%a8%9a-1-%e0%a8%ae%e0%a8%bf/"},{"Title":"ਦਿੱਲੀ ਦੀ ਗੁਰਦਵਾਰਾ ਸਿਆਸਤ ਕੋਰੋਨਾ ਨੂੰ ਲੈ ਕੇ ਇਕ-ਦੂਜੇ ਵਿਰੁਧ ਡਟੀ","Content":"ਨਵੀਂ ਦਿੱਲੀ  : &#8216;ਜਾਗੋ&#8217; ਪਾਰਟੀ ਦੇ ਪ੍ਰਧਾਨ ਸ.ਮਨਜੀਤ ਸਿੰਘ ਜੀ ਕੇ ਨੇ ਦੋਸ਼ ਲਾਇਆ ਹੈ ਕਿ ਦਿੱਲੀ ਸਿੱਖ ਗੁਰਦਵਾਰਾ ਪ੍ਰਬੰਧਕ","PublishDate":"Fri, 10 Apr 2020 06:10:37 +00:00","Link":"http://punjabnewsusa.com/top-news/%e0%a8%a6%e0%a8%bf%e0%a9%b1%e0%a8%b2%e0%a9%80-%e0%a8%a6%e0%a9%80-%e0%a8%97%e0%a9%81%e0%a8%b0%e0%a8%a6%e0%a8%b5%e0%a8%be%e0%a8%b0%e0%a8%be-%e0%a8%b8%e0%a8%bf%e0%a8%86%e0%a8%b8%e0%a8%a4-%e0%a8%95/"},{"Title":"ਬਿਆਸ ਦਰਿਆ ਵਿਚ ਡੁੱਬੇ ਤਿੰਨ ਨੌਜਵਾਨਾਂ ਦੀ 11 ਦਿਨਾਂ ਤੋਂ ਭਾਲ ਜਾਰੀ","Content":"ਢਿੱਲਵਾਂ : ਬੀਤੀ 29 ਮਾਰਚ ਨੂੰ ਬਿਆਸ ਦਰਿਆ ਵਿਚ ਮੱਛੀਆਂ ਫੜਨ ਗਏ ਤਿੰਨ ਨੌਜਵਾਨ ਸੁਖਵਿੰਦਰ ਸਿੰਘ, ਸਤਨਾਮ ਸਿੰਘ, ਜੈਕਸਨ ਦਰਿਆ","PublishDate":"Fri, 10 Apr 2020 06:09:53 +00:00","Link":"http://punjabnewsusa.com/featured/%e0%a8%ac%e0%a8%bf%e0%a8%86%e0%a8%b8-%e0%a8%a6%e0%a8%b0%e0%a8%bf%e0%a8%86-%e0%a8%b5%e0%a8%bf%e0%a8%9a-%e0%a8%a1%e0%a9%81%e0%a9%b1%e0%a8%ac%e0%a9%87-%e0%a8%a4%e0%a8%bf%e0%a9%b0%e0%a8%a8-%e0%a8%a8/"},{"Title":"ਦਿੱਲੀ ‘ਚ ਸਿੱਖ ਤੇ ਪੰਜਾਬੀ ਨੌਜਵਾਨ ਵੀ ਕਰ ਰਹੇ ਹਨ ਲੋੜਵੰਦਾਂ ਦੀ ਮਦਦ","Content":"ਨਵੀਂ ਦਿੱਲੀ : ਤਾਲਾਬੰਦੀ ਵਿਚ  ਲਾਚਾਰੀ ਦੀ ਹਾਲਤ &#8216;ਚ ਜੀਅ ਰਹੇ ਗ਼ਰੀਬਾਂ ਨੂੰ ਰਾਸ਼ਨ ਆਦਿ ਵੰਡ ਕੇ, ਨੌਜਵਾਨਾਂ ਦੀ ਜਥੇਬੰਦੀ","PublishDate":"Fri, 10 Apr 2020 06:08:01 +00:00","Link":"http://punjabnewsusa.com/top-news/%e0%a8%a6%e0%a8%bf%e0%a9%b1%e0%a8%b2%e0%a9%80-%e0%a8%9a-%e0%a8%b8%e0%a8%bf%e0%a9%b1%e0%a8%96-%e0%a8%a4%e0%a9%87-%e0%a8%aa%e0%a9%b0%e0%a8%9c%e0%a8%be%e0%a8%ac%e0%a9%80-%e0%a8%a8%e0%a9%8c%e0%a8%9c/"},{"Title":"ਕੋਰੋਨਾ ਜੰਗ ਦੌਰਾਨ ਬਲੀਦਾਨ ਦੇਣ ਲਈ ਤਿਆਰ ਯੂਪੀ ਦੇ ਹਰਕੀਰਤ ਸਿੰਘ","Content":"ਲਖਨਊ: ਕੋਰੋਨਾ ਵਾਇਰਸ ਨੂੰ ਲੈ ਕੇ ਹਰ ਪਾਸੇ ਦਹਿਸ਼ਤ ਦਾ ਮਾਹੌਲ ਹੈ। ਇਸ ਸਮੇਂ ਕੁਝ ਲੋਕ ਅਜਿਹੇ ਵੀ ਹਨ ਜੋ","PublishDate":"Fri, 10 Apr 2020 06:07:08 +00:00","Link":"http://punjabnewsusa.com/top-news/%e0%a8%95%e0%a9%8b%e0%a8%b0%e0%a9%8b%e0%a8%a8%e0%a8%be-%e0%a8%9c%e0%a9%b0%e0%a8%97-%e0%a8%a6%e0%a9%8c%e0%a8%b0%e0%a8%be%e0%a8%a8-%e0%a8%ac%e0%a8%b2%e0%a9%80%e0%a8%a6%e0%a8%be%e0%a8%a8-%e0%a8%a6/"},{"Title":"ਕੈਪਟਨ ਸਰਕਾਰ ਦਾ ਵੱਡਾ ਕਦਮ, ਪੰਜਾਬ ਵਿਚ ਮਾਸਕ ਲਾਉਣਾ ਹੋਇਆ ਲਾਜ਼ਮੀ","Content":"ਚੰਡੀਗੜ੍ਹ- ਕੋਰੇਨਾ ਖ਼ਿਲਾਫ਼ ਜੰਗ ਵਿਚ ਪੰਜਾਬ ਦੀ ਕੈਪਟਨ ਸਰਕਾਰ ਨੇ ਵੱਡਾ ਕਦਮ ਚੁੱਕਿਆ ਹੈ। ਰਾਜ ਵਿਚ ਮਾਸਕ ਪਹਿਨਣਾ ਲਾਜ਼ਮੀ ਕਰ","PublishDate":"Fri, 10 Apr 2020 06:06:12 +00:00","Link":"http://punjabnewsusa.com/featured/%e0%a8%95%e0%a9%88%e0%a8%aa%e0%a8%9f%e0%a8%a8-%e0%a8%b8%e0%a8%b0%e0%a8%95%e0%a8%be%e0%a8%b0-%e0%a8%a6%e0%a8%be-%e0%a8%b5%e0%a9%b1%e0%a8%a1%e0%a8%be-%e0%a8%95%e0%a8%a6%e0%a8%ae-%e0%a8%aa%e0%a9%b0/"},{"Title":"ਉੱਚੀ ਮੌਤ ਦਰ ਕਾਰਨ ‘ਹਾਟਸਪਾਟ’ ‘ਚ ਬਦਲਿਆ ਸੱਭ ਤੋਂ ਸੋਹਣਾ ਸ਼ਹਿਰ","Content":"ਇੰਦੌਰ : ਆਰਥਕ, ਸਮਾਜਕ ਅਤੇ ਸਭਿਆਚਾਰਕ ਗਤੀਵਿਧੀਆਂ ਵਿਚ ਹਮੇਸ਼ਾ ਗੁਲਜ਼ਾਰ ਰਹਿਣ ਵਾਲਾ ਮੱਧ ਪ੍ਰਦੇਸ਼ ਦਾ ਸੱਭ ਤੋਂ ਵੱਡਾ ਅਤੇ ਸੋਹਣਾ","PublishDate":"Fri, 10 Apr 2020 06:03:38 +00:00","Link":"http://punjabnewsusa.com/top-news/%e0%a8%89%e0%a9%b1%e0%a8%9a%e0%a9%80-%e0%a8%ae%e0%a9%8c%e0%a8%a4-%e0%a8%a6%e0%a8%b0-%e0%a8%95%e0%a8%be%e0%a8%b0%e0%a8%a8-%e0%a8%b9%e0%a8%be%e0%a8%9f%e0%a8%b8%e0%a8%aa%e0%a8%be%e0%a8%9f-%e0%a8%9a/"},{"Title":"COVID 19: ਦੁਨੀਆ ਭਰ ਵਿਚ 15 ਲੱਖ ਤੋਂ ਵੱਧ ਸੰਕਰਮਿਤ, ਮੌਤਾਂ ਦੀ ਗਿਣਤੀ 90 ਹਜ਼ਾਰ ਤੋਂ ਪਾਰ","Content":"ਪੈਰਿਸ- ਕੋਰੋਨਾ ਵਾਇਰਸ ਦੀ ਮਹਾਂਮਾਰੀ ਵਿਸ਼ਵ ਭਰ ਵਿੱਚ 90,000 ਦਾ ਅੰਕੜਾ ਪਾਰ ਕਰ ਗਈ ਹੈ। 90,938 ਮਾਮਲਿਆਂ ਵਿਚ ਹੋਈਆਂ ਕੁੱਲ","PublishDate":"Thu, 09 Apr 2020 20:14:05 +00:00","Link":"http://punjabnewsusa.com/top-news/covid-19-%e0%a8%a6%e0%a9%81%e0%a8%a8%e0%a9%80%e0%a8%86-%e0%a8%ad%e0%a8%b0-%e0%a8%b5%e0%a8%bf%e0%a8%9a-15-%e0%a8%b2%e0%a9%b1%e0%a8%96-%e0%a8%a4%e0%a9%8b%e0%a8%82-%e0%a8%b5%e0%a9%b1%e0%a8%a7-%e0%a8%b8/"},{"Title":"ਓਪੀਡੀ ਖੋਲ੍ਹਣ ਦੀ ਜ਼ਰੂਰਤ","Content":"ਕਰੋਨਾਵਾਇਰਸ ਦੀ ਮਹਾਮਾਰੀ ਨਾਲ ਜੂਝਣ ਲਈ ਹਾਲਾਂਕਿ ਵਿਆਪਕ ਰਣਨੀਤੀ ਦੀ ਲੋੜ ਹੈ ਪਰ ਇਸ ਲੜਾਈ ਵਿਚ ਸਿਹਤ ਸਹੂਲਤਾਂ ਸਭ ਤੋਂ","PublishDate":"Wed, 08 Apr 2020 05:45:45 +00:00","Link":"http://punjabnewsusa.com/article/%e0%a8%93%e0%a8%aa%e0%a9%80%e0%a8%a1%e0%a9%80-%e0%a8%96%e0%a9%8b%e0%a8%b2%e0%a9%8d%e0%a8%b9%e0%a8%a3-%e0%a8%a6%e0%a9%80-%e0%a8%9c%e0%a8%bc%e0%a8%b0%e0%a9%82%e0%a8%b0%e0%a8%a4/"},{"Title":"ਜਿਓਤੀ ਰਾਓ ਗੋਬਿੰਦ ਰਾਓ ਫੂਲੇ (ਸੰਖੇਪ ਜੀਵਨੀ)","Content":"<p>ਰਵਾਇਤੀ ਤੌਰ ’ਤੇ ਗੱਲ ਕਰਦਿਆਂ ਜਯੋਤੀ ਰਾਓ ਫੂਲੇ ਦਾ ਜਨਮ 1827 ਵਿੱਚ ਗੋਬਿੰਦ ਰਾਓ ਫੂਲੇ ਦੇ ਘਰ ਮਹਾਰਾਸ਼ਟਰ ਦੇ ਸਤਾਰਾ ਜਿਲ੍ਹੇ ਦੇ ਕਾਤਗੁਨ ਵਿਖੇ ਹੋਇਆ। ਵਰਨ ਵੰਡ ਦੀ ਤੁਰੀ ਆ ਰਹੀ ਰਵਾਇਤ ਅਨੁਸਾਰ ਉਹ ਮਾਲੀ ਜਾਤ ਨਾਲ ਸਬੰਧ ਰੱਖਦੇ ਸਨ ਤੇ ਇਸੇ ਕਾਰਨ ਫੁੱਲਾਂ ਦਾ ਕੰਮ ਕਰਦੇ ਹੋਣ ਕਰਕੇ ਉਨ੍ਹਾਂ ਨੂੰ ਫੂਲੇ ਕਿਹਾ ਜਾਣ ਲੱਗਿਆ।</p>\n<p><a rel=\"nofollow\" href=\"https://www.sikhsiyasat.info/2020/04/jyoti-rao-phule/\">ਜਿਓਤੀ ਰਾਓ ਗੋਬਿੰਦ ਰਾਓ ਫੂਲੇ (ਸੰਖੇਪ ਜੀਵਨੀ)</a> appeared first on <a rel=\"nofollow\" href=\"https://www.sikhsiyasat.info\">Sikh Siyasat News</a>.</p>\n","PublishDate":"Sat, 11 Apr 2020 13:23:17 +00:00","Link":"https://www.sikhsiyasat.info/2020/04/jyoti-rao-phule/"},{"Title":"ਅਮਲੀ ਸਿਖ-ਜੀਵਨ ","Content":"<p>ਜਦ ਤਕ ਤੁਸੀਂ ਕਰਤਾ ਪੁਰਖ ਦੇ ਆਦਰਸ਼ ਨੂੰ ਜਾਣ ਕੇ ਕੋਮਲ ਹੁਨਰ, ਦਸਤਕਾਰੀ ਅਤੇ ਕਾਰੀਗਰੀ ਵਿਚ ਕਮਾਲ ਹਾਸਲ ਨਹੀਂ ਕਰ ਲੈਂਦੇ; ਜਦ ਤਕ ਤੁਸੀਂ ਦਿਲ ਤੇ ਦਿਮਾਗ ਨੂੰ ਉੱਚਾ ਨਹੀਂ ਕਰ ਲੈਂਦੇ; ਤਦ ਤਕ ਕੁਰਬਾਨੀ ਕਰ ਕੇ ਵੀ ਹਾਰ ਹੈ ਤੇ ਤੁਹਾਡੀਆਂ ਜਿੱਤਾਂ ਵੀ ਹਾਰ ਦੀ ਸ਼ਕਲ ਵਿਚ ਹਨ। </p>\n<p><a rel=\"nofollow\" href=\"https://www.sikhsiyasat.info/2020/04/article-by-prof-puran-singh-ji-2/\">ਅਮਲੀ ਸਿਖ-ਜੀਵਨ </a> appeared first on <a rel=\"nofollow\" href=\"https://www.sikhsiyasat.info\">Sikh Siyasat News</a>.</p>\n","PublishDate":"Fri, 10 Apr 2020 12:49:49 +00:00","Link":"https://www.sikhsiyasat.info/2020/04/article-by-prof-puran-singh-ji-2/"},{"Title":"ਕੋਰੋਨਾ ਤੋਂ ਬਾਅਦ ਦੇ ਅਣਕਿਆਸੇ ਜਗਤ ਲਈ ਤਿਆਰ ਰਹੋ","Content":"<p>ਜਿਦੰਗੀ ਦੀ  ਹਰ ਸਰਗਰਮੀ ਦਾ ਵੇਰਵਾ ਹੁਕਮਤ ਪਾਸ ਹੋਵੇਗਾ ਤੇ ਇਹ ਨਿਗਰਾਨੀ ਬਿਮਾਰੀ ਤੋਂ ਬਾਅਦ ਦੇ ਹਲਾਤਾਂ ਵਿੱਚ ਵੀ ਜਾਰੀ ਰੱਖੀ ਜਾਵੇਗੀ। ਅਜਿਹੀ ਤਕਨਾਲੋਜੀ ਬਹੁਤ ਸਾਰੇ ਦੇਸ਼ਾਂ ਵਿਚ ਨਿਗਰਾਨੀ ਕਰਨ ਲਈ ਵਰਤੀ ਜਾ ਰਹੀ  ਹੈ।</p>\n<p><a rel=\"nofollow\" href=\"https://www.sikhsiyasat.info/2020/04/corona-changing-world-be-ready-for-unimagined-new/\">ਕੋਰੋਨਾ ਤੋਂ ਬਾਅਦ ਦੇ ਅਣਕਿਆਸੇ ਜਗਤ ਲਈ ਤਿਆਰ ਰਹੋ</a> appeared first on <a rel=\"nofollow\" href=\"https://www.sikhsiyasat.info\">Sikh Siyasat News</a>.</p>\n","PublishDate":"Thu, 09 Apr 2020 16:47:04 +00:00","Link":"https://www.sikhsiyasat.info/2020/04/corona-changing-world-be-ready-for-unimagined-new/"},{"Title":"ਅੱਜ ਆਪਾ ਜੋਖੋ!","Content":"<p>ਗੁਰ ਸਿੱਖੀ ਇਕ ਕਿਰਤ ਹੈ, ਕਰਨੀ ਹੈ, ਰਹਿਣੀ ਹੈ- “ਰਹਿਣੀ ਰਹੈ ਸੋਈ ਸਿਖ ਮੇਰਾ”। ਸਿੱਖੀ ਕੋਈ ਮਜ਼੍ਹਬੀ ਫ਼ਿਰਕਾਬੰਦੀ ਨਹੀਂ, ਪਿਆਰ ਦੀ ਬਰਾਦਰੀ ਹੈ, ਸੇਵਾ ਦਾ ਜੱਥਾ ਹੈ, ਰੱਬ ਦੀ ਬਾਣੀ ਦੀ ਮੂਰਤ ਹੈ “ਸਬਦੁ ਗੁਰੂ ਸੁਰਤਿ ਧੁਨਿ ਚੇਲਾ॥” ਇਹ ਧਰਮ ਦੀ ਬਾਦਸ਼ਾਹੀ ਹੈ। ਇਹ ਗੁਰੂ ਦਾ ਪਿਆਰ ਹੈ; ਅਖੰਡ ਬਲਨ ਵਾਲੀ ਪਿਆਰ-ਜੋਤ ਹੈ।</p>\n<p><a rel=\"nofollow\" href=\"https://www.sikhsiyasat.info/2020/04/article-by-prof-puran-singh-ji/\">ਅੱਜ ਆਪਾ ਜੋਖੋ!</a> appeared first on <a rel=\"nofollow\" href=\"https://www.sikhsiyasat.info\">Sikh Siyasat News</a>.</p>\n","PublishDate":"Thu, 09 Apr 2020 09:38:10 +00:00","Link":"https://www.sikhsiyasat.info/2020/04/article-by-prof-puran-singh-ji/"},{"Title":"ਗੁਰੂ ਨਾਨਕ ਜੀ ਦੀ ਰਸੈਣ","Content":"<p>ਉਹਨਾਂ ਦੀ ਨਿਗਾਹ ਹੀ ਅਕਸੀਰ ਸੀ। ਨੀਵਿਆਂ ਮਨਾਂ ਨੂੰ ਉਚੇ ਕਰਨ ਦੀ ਰਸੈਣ। ਰਸੈਣ ਬਨਾਉਣਾ ਹੈ ਮੈਲੇ ਦਿਲਾਂ ਨੂੰ ਧੋ ਕੱਢਣਾ। ਉਹਨਾਂ ਦੇ ਔਗੁਣ ਕੱਢਕੇ ਗੁਣ ਭਰ ਦੇਣੇ, ਸਭ ਤੋਂ ਵੱਧ ਉਹਨਾਂ ਦਿਲਾਂ ਵਿਚ ਨਿਰੰਕਾਰ ਦਾ ਪ੍ਰੇਮ ਭਰ ਦੇਣਾ ਤੇ ਪ੍ਰੇਮ ਭਰਕੇ ਪਰੇਮ ਵਿਚ ਨਿਰਾ ਮਗਨ ਹੀ ਨਾ ਕਰ ਦੇਣਾ ਪਰ ਪਰੇਮ ਵੰਡਣਾ ਬੀ ਸਿਖਾਲ ਦੇਣਾ, ਸਰਬਤ ਦੇ ਭਲੇ ਦੀ ਜਾਚ ਤੇ ਉੱਦਮ ਭਰ ਦੇਣਾ।</p>\n<p><a rel=\"nofollow\" href=\"https://www.sikhsiyasat.info/2020/04/article-bhai-veer-singh/\">ਗੁਰੂ ਨਾਨਕ ਜੀ ਦੀ ਰਸੈਣ</a> appeared first on <a rel=\"nofollow\" href=\"https://www.sikhsiyasat.info\">Sikh Siyasat News</a>.</p>\n","PublishDate":"Wed, 08 Apr 2020 14:07:25 +00:00","Link":"https://www.sikhsiyasat.info/2020/04/article-bhai-veer-singh/"},{"Title":"ਟਰੰਪ ਦੀ ਧਮਕੀ ਅੱਗੇ ਮੋਦੀ ਝੁੱਕਿਆ-ਜਸਪਾਲ ਸਿੰਘ ਸਿੱਧੂ","Content":"<p>ਕੇਵਲ ਤਾਲਾਬੰਦੀ ਬੁਨਿਆਦੀ ਮੈਡੀਕਲ ਢਾਂਚੇ ਦਾ ਬਦਲ ਨਹੀਂ ਹੋ ਸਕਦਾ। ਇਸੇ ਕਰਕੇ ਮੁੱਖ ਮੰਤਰੀ ਆਪਣੀ ਕੁਰਸੀਆਂ ਨੂੰ ਬਚਾਉਣ ਹਿਤ ਤਾਲਾਬੰਦੀ ਨੂੰ 14 ਅਪ੍ਰੈਲ ਤੋਂ ਅੱਗੇ ਵਧਾਉਣ ਦੇ ਹੱਕ ਵਿਚ ਨਹੀਂ ਹਨ। ਅਤੇ ਕੇਂਦਰ ਵੀ ਉਹਨਾਂ ਕੋਈ ਸਹਾਇਤਾ ਨਹੀ ਕਰ ਰਿਹਾ ।</p>\n<p><a rel=\"nofollow\" href=\"https://www.sikhsiyasat.info/2020/04/modi-yields-when-trump-threatened-to-retaliate/\">ਟਰੰਪ ਦੀ ਧਮਕੀ ਅੱਗੇ ਮੋਦੀ ਝੁੱਕਿਆ-ਜਸਪਾਲ ਸਿੰਘ ਸਿੱਧੂ</a> appeared first on <a rel=\"nofollow\" href=\"https://www.sikhsiyasat.info\">Sikh Siyasat News</a>.</p>\n","PublishDate":"Tue, 07 Apr 2020 13:59:04 +00:00","Link":"https://www.sikhsiyasat.info/2020/04/modi-yields-when-trump-threatened-to-retaliate/"},{"Title":"ਪੰਜਾਬ ਦੇ ਲੋਕ ਮੋਦੀ ਦੇ 9 ਵਜੇ, 9 ਮਿੰਟ ਵਾਲੇ ਵਹਿਮੀ ਸੱਦੇ ਨੂੰ ਨਕਾਰਨ: ਦਲ ਖਾਲਸਾ","Content":"<p>ਭਾਰਤ ਦੇ ਪ੍ਰਧਾਨ ਮੰਤਰੀ ਨਰਿੰਦਰ ਮੋਦੀ ਵਲੋਂ ਕੋਰੋਨਾ ਵਾਈਰਸ ਨਾਲ ਨਜਿਠਣ ਲਈ ਐਤਵਾਰ ਰਾਤ 9 ਵਜੇ 9 ਮਿੰਟ ਲਈ ਘਰਾਂ ਦੀਆਂ ਬੱਤੀਆਂ ਬੁਝਾ ਕੇ ਮੋਮਬੱਤੀਆਂ ਅਤੇ ਦੀਵੇ ਜਗਾਉਣ ਦੇ ਦਿੱਤੇ ਸੱਦੇ ਦਾ ਤਿੱਖਾ ਵਿਰੋਧ ਕਰਦਿਆਂ ਦਲ ਖਾਲਸਾ ਨੇ ਇਸ ਨੂੰ ਖੋਖਲਾ ਪ੍ਰਤੀਕਵਾਦ ਦਸਿਆ ਜੋ ਅੰਕ ਵਿਗਿਆਨ ਜੋਤਿਸ਼ 'ਤੇ ਆਧਾਰਿਤ ਹੈ।</p>\n<p><a rel=\"nofollow\" href=\"https://www.sikhsiyasat.info/2020/04/dal-khalsa-calls-to-reject-modis-call/\">ਪੰਜਾਬ ਦੇ ਲੋਕ ਮੋਦੀ ਦੇ 9 ਵਜੇ, 9 ਮਿੰਟ ਵਾਲੇ ਵਹਿਮੀ ਸੱਦੇ ਨੂੰ ਨਕਾਰਨ: ਦਲ ਖਾਲਸਾ</a> appeared first on <a rel=\"nofollow\" href=\"https://www.sikhsiyasat.info\">Sikh Siyasat News</a>.</p>\n","PublishDate":"Sun, 05 Apr 2020 02:35:39 +00:00","Link":"https://www.sikhsiyasat.info/2020/04/dal-khalsa-calls-to-reject-modis-call/"},{"Title":"ਪ੍ਰੋ. ਦਵਿੰਦਰਪਾਲ ਸਿੰਘ ਭੁੱਲਰ ਜੇਲ੍ਹ ਵਿੱਚੋਂ 6 ਹਫਤੇ ਦੀ ਪੇਰੋਲ ਉੱਤੇ ਰਿਹਾਅ","Content":"<p>ਬੰਦੀ ਸਿੰਘ ਪ੍ਰੋ. ਦਵਿੰਦਰਪਾਲ ਸਿੰਘ ਭੁੱਲਰ ਬੀਤੇ ਕੱਲ੍ਹ ਪੇਰੋਲ ਉੱਤੇ ਰਿਹਾਅ ਹੋਏ ਹਨ। ਇਸ ਬਾਰੇ ਜਾਣਕਾਰੀ ਦਿੰਦਿਆਂ ਪ੍ਰੋ. ਦਵਿੰਦਰਪਾਲ ਸਿੰਘ ਭੁੱਲਰ ਦੇ ਵਕੀਲ ਅਤੇ ਸਿੰਘਾਂ ਦੀ ਸੂਚੀ ਤਿਆਰ ਕਰਨ ਵਾਲੇ ਐਡਵੋਕੇਟ ਜਸਪਾਲ ਸਿੰਘ ਮੰਝਪੁਰ ਨੇ ਦੱਸਿਆ ਕਿ ਪ੍ਰੋ. ਭੁੱਲਰ 6 ਹਫਤੇ ਦੀ ਪੇਰੋਲ (ਛੁੱਟੀ) ਉੱਤੇ ਰਿਹਾਅ ਹੋਏ ਹਨ।</p>\n<p><a rel=\"nofollow\" href=\"https://www.sikhsiyasat.info/2020/04/prof-bhullar-parole/\">ਪ੍ਰੋ. ਦਵਿੰਦਰਪਾਲ ਸਿੰਘ ਭੁੱਲਰ ਜੇਲ੍ਹ ਵਿੱਚੋਂ 6 ਹਫਤੇ ਦੀ ਪੇਰੋਲ ਉੱਤੇ ਰਿਹਾਅ</a> appeared first on <a rel=\"nofollow\" href=\"https://www.sikhsiyasat.info\">Sikh Siyasat News</a>.</p>\n","PublishDate":"Sat, 04 Apr 2020 14:49:01 +00:00","Link":"https://www.sikhsiyasat.info/2020/04/prof-bhullar-parole/"},{"Title":"ਰਾਜ ਕਰੇਗਾ ਖ਼ਾਲਸਾ ਆਕੀ ਰਹੇ ਨ ਕੋਇ","Content":"<p>ਦੁਨੀਆ ਗਈ ਤਾਂ ਲਾਲਚ ਮੋਇਆ, ਜਿਥੇ ਲਾਲਚ ਨਹੀਂ ਉਥੇ ਖੋਹਣ-ਖਿੱਚਣ ਤੇ ਚੋਰੀ-ਧਾੜੇ ਕਾਹਦੇ ? ਜੇ ਚੋਰੀ ਨਹੀਂ ਤਾਂ ਰਾਖੀ ਕਿਉਂ ? ਜੇ ਰਖਵਾਲੀ ਨਹੀਂ ਤਾਂ ਖ਼ਰਾਜ ਕਿਉਂ ? ਇਹ ਤਾਂ ਸਾਰਾ ਢਾਂਚਾ ਹੀ ਲਾਲਚ ਦੇ ਸਿਰ 'ਤੇ ਖਲੋਤਾ ਹੋਇਆ ਹੈ।</p>\n<p><a rel=\"nofollow\" href=\"https://www.sikhsiyasat.info/2020/04/khalsa-raj-article/\">ਰਾਜ ਕਰੇਗਾ ਖ਼ਾਲਸਾ ਆਕੀ ਰਹੇ ਨ ਕੋਇ</a> appeared first on <a rel=\"nofollow\" href=\"https://www.sikhsiyasat.info\">Sikh Siyasat News</a>.</p>\n","PublishDate":"Sat, 04 Apr 2020 06:02:58 +00:00","Link":"https://www.sikhsiyasat.info/2020/04/khalsa-raj-article/"},{"Title":"ਸਾਡੇ ਵਡੇਰੇ ਕਿੰਨੀ ਦੂਰ ਤੱਕ ਵੇਖ ਸਕਦੇ ਸਨ: 1832 ‘ਚ ਲੁਧਿਆਣਿਓਂ ਵੀ ਧੌਲੀਧਾਰ ਪਹਾੜ ਲੜੀ ਸਾਫ ਦਿਸਦੀ ਹੁੰਦੀ ਸੀ","Content":"<p>ਏਅਰ ਪਲਿਊਸ਼ਨ (ਹਵਾ ਵਿਚਲੇ ਪਰਦੂਸ਼ਣ) ਦੇ ਹਵਾਲੇ ਨਾਲ ਜਦੋਂ ਮੈਂ ਕਿਸੇ ਨੂੰ ਦੱਸਿਆ ਕਰਨਾ ਕਿ ਕੋਈ ਵੇਲਾ ਹੁੰਦਾ ਸੀ ਜਦੋਂ ਬਰਫ਼ ਨਾਲ ਲੱਦੇ ਧੌਲੀਧਾਰ ਦੇ ਪਹਾੜ ਲੁਧਿਆਣੇ ਤੋਂ ਸਾਫ਼ ਦਿਸਦੇ ਹੁੰਦੇ ਸੀ ਤਾਂ ਕੋਈ ਏਹ ਗੱਲ ਮੰਨਣ ਤਿਆਰ ਨਹੀਂ ਸੀ ਹੁੰਦਾ।</p>\n<p><a rel=\"nofollow\" href=\"https://www.sikhsiyasat.info/2020/04/dhauladhar-mountain-range-news/\">ਸਾਡੇ ਵਡੇਰੇ ਕਿੰਨੀ ਦੂਰ ਤੱਕ ਵੇਖ ਸਕਦੇ ਸਨ: 1832 &#8216;ਚ ਲੁਧਿਆਣਿਓਂ ਵੀ ਧੌਲੀਧਾਰ ਪਹਾੜ ਲੜੀ ਸਾਫ ਦਿਸਦੀ ਹੁੰਦੀ ਸੀ</a> appeared first on <a rel=\"nofollow\" href=\"https://www.sikhsiyasat.info\">Sikh Siyasat News</a>.</p>\n","PublishDate":"Fri, 03 Apr 2020 14:18:38 +00:00","Link":"https://www.sikhsiyasat.info/2020/04/dhauladhar-mountain-range-news/"}]